{
	"_meta": {
		"dependencies": {
			"monster": [
				"MM",
				"SKT",
				"MTF"
			]
		},
		"otherSources": {
			"monster": {
				"MM": "BGDIA",
				"ToA": "BGDIA",
				"MTF": "BGDIA",
				"VGM": "BGDIA",
				"RoT": "BGDIA",
				"DMG": "BGDIA"
			}
		},
		"internalCopies": [
			"monstre"
		]
	},
	"monster": [
		{
			"name": "Pollastre abissal",
			"source": "BGDIA",
			"page": 97,
			"size": "T",
			"type": {
				"type": "infernal",
				"tags": [
					"dimoni"
				]
			},
			"alineament": [
				"C",
				"E"
			],
			"ac": [
				{
					"ac": 13,
					"from": [
						"armadura natural"
					]
				}
			],
			"hp": {
				"average": 10,
				"formula": "3d4 + 3"
			},
			"speed": {
				"walk": 30,
				"volar": {
					"number": 30,
					"condition": "(vegeu el mal volant a continuació)"
				}
			},
			"str": 6,
			"dex": 14,
			"con": 13,
			"int": 4,
			"wis": 9,
			"cha": 5,
			"senses": [
				"visió a cegues 30ft. (sens visió més enllà)"
			],
			"passive": 9,
			"resist": [
				"fred",
				"foc",
				"elèctric"
			],
			"immune": [
				"verí"
			],
			"conditionImmune": [
				"encegat",
				"emmetzinat"
			],
			"idiomes": [
				"entén Abyssal però no pot parlar"
			],
			"cr": "1/4",
			"trait": [
				{
					"name": "Mala Voladora",
					"entries": [
						"El pollastre abissal cau al final d'un gir si està en l'aire i l'únic que el manté en alt és la seva velocitat de vol."
					]
				}
			],
			"action": [
				{
					"name": "Multiatac",
					"entries": [
						"El pollastre abissal fa dos atacs: un amb la seva mossegada i un altre amb les urpes."
					]
				},
				{
					"name": "Mossegada",
					"entries": [
						"{@atk mw} {@hit 4} a impactar, 5 peus d'abast, una criatura. {@h}4 ({@damage 1d4 + 2}) de dany perforant."
					]
				},
				{
					"name": "Urpes",
					"entries": [
						"{@atk mw} {@hit 4} a impactar, 5 peus d'abast, un objectiu. {@h}5 ({@damage 1d6 + 2}) de dany tallant."
					]
				}
			],
			"familiar": true,
			"hasToken": true,
			"senseTags": [
				"B"
			],
			"actionTags": [
				"Multiatac"
			],
			"languageTags": [
				"AB",
				"CS"
			],
			"damageTags": [
				"P",
				"S"
			],
			"miscTags": [
				"MW"
			],
			"hasFluff": true,
			"hasFluffImages": true
		},
		{
			"name": "Amrik Vanthampur",
			"isNpc": true,
			"source": "BGDIA",
			"page": 30,
			"size": "M",
			"type": {
				"type": "humanoide",
				"tags": [
					"humà"
				]
			},
			"alineament": [
				"L",
				"E"
			],
			"ac": [
				{
					"ac": 17,
					"from": [
						"{@item armadura de cuir|phb}",
						"modificador de carisma"
					]
				}
			],
			"hp": {
				"average": 66,
				"formula": "12d8 + 12"
			},
			"speed": {
				"walk": 30
			},
			"str": 12,
			"dex": 18,
			"con": 12,
			"int": 14,
			"wis": 14,
			"cha": 15,
			"skill": {
				"acrobatics": "+6",
				"athletics": "+3",
				"deception": "+6",
				"insight": "+6"
			},
			"passive": 12,
			"idiomes": [
				"Comú",
				"Diàstric"
			],
			"cr": "3",
			"trait": [
				{
					"name": "Defensa Suave",
					"entries": [
						"Mentre Amrik porta una armadura lleugera o sense armadura i no porta cap escut, la seva CA inclou el seu modificador de Carisma."
					]
				}
			],
			"action": [
				{
					"name": "Multiatac",
					"entries": [
						"Amrik fa tres atacs de punyal."
					]
				},
				{
					"name": "Daga",
					"entries": [
						"{@atk mw,rw} {@hit 6} a impactar, 5 peus d'abast o 20/60 peus d'abast, un objectiu. {@h}6 ({@damage 1d4 + 4}) de dany perforant."
					]
				},
				{
					"name": "Bomba de fum (1/dia)",
					"entries": [
						"Amrik llança una aleta de bomba de fum a 20 peus de distància. La bomba explota en l'impacte, creant un núvol de fum negre que omple una esfera de 10 peus de radi. L'àrea dins del núvol està molt enfosquida. Un fort vent dispersa el núvol, que d'altra manera romandrà fins al final del següent torn d'Amrik."
					]
				}
			],
			"hasToken": true,
			"actionTags": [
				"Multiatac"
			],
			"languageTags": [
				"C",
				"I"
			],
			"damageTags": [
				"P"
			],
			"miscTags": [
				"AOE",
				"MW",
				"RW",
				"THW"
			],
			"hasFluff": true,
			"hasFluffImages": true
		},
		{
			"name": "Arxiduc Zariel d'Averno",
			"isNpc": true,
			"source": "BGDIA",
			"page": 243,
			"_copy": {
				"name": "Zariel",
				"source": "MTF",
				"_mod": {
					"action": [
						{
							"mode": "substituirArr",
							"replace": "Multiatac",
							"items": {
								"name": "Multiatac",
								"entries": [
									"La Zariel ataca dues vegades amb el seu flagell i una altra amb Matalotok. Pot substituir Horrid Touch per Matalotok."
								]
							}
						},
						{
							"mode": "substituirArr",
							"replace": "Espasa llarga",
							"items": {
								"name": "Flau",
								"entries": [
									"{@atk mw} {@hit 16} a impactar, 10 peus d'abast, un objectiu. {@h}17 ({@damage 2d8 + 8}) de dany perforant mes 36 ({@damage 8d8}) de dany de foc."
								]
							}
						},
						{
							"mode": "substituirArr",
							"replace": "Javelina",
							"items": {
								"name": "Matalotok (Martell de guerra)",
								"entries": [
									"{@atk mw} {@hit 16} a impactar, 10 peus d'abast, un objectiu. {@h}17 ({@damage 2d8 + 8}) bludgeoning, o 19 ({@damage 2d10 + 8}) de dany contundent si s'usa amb dues mans, plus 36 ({@damage 8d8}) de dany de foc. A més, l'arma emet un esclat de fred que infligeix ​​10 ({@damage 3d6}) de dany de fred a cada criatura a 30 peus d'ella."
								]
							}
						}
					]
				}
			},
			"resist": [
				"foc",
				"radiant",
				{
					"resist": [
						"contundent",
						"perforant",
						"tallant"
					],
					"note": "d'atacs no màgics amb armes no platejades",
					"cond": true
				}
			],
			"immune": [
				"fred",
				"necròtic",
				"verí"
			],
			"hasToken": true,
			"damageTags": [
				"B",
				"C",
				"F",
				"N",
				"P"
			],
			"miscTags": [
				"MW",
				"RCH"
			],
			"hasFluff": true,
			"hasFluffImages": true
		},
		{
			"name": "Arkhan el Cruel",
			"isNpc": true,
			"source": "BGDIA",
			"page": 111,
			"size": "M",
			"type": {
				"type": "humanoide",
				"tags": [
					"sang de drac"
				]
			},
			"alineament": [
				"L",
				"E"
			],
			"ac": [
				{
					"ac": 23,
					"from": [
						"{@item placa de drac de sílex d'obsidiana|bgdia}",
						"{@item shield|phb}"
					]
				}
			],
			"hp": {
				"average": 221,
				"formula": "26d8 + 104"
			},
			"speed": {
				"walk": 40
			},
			"str": 20,
			"dex": 12,
			"con": 18,
			"int": 10,
			"wis": 10,
			"cha": 18,
			"save": {
				"wis": "+5",
				"cha": "+9"
			},
			"skill": {
				"athletics": "+10",
				"deception": "+9",
				"intimidation": "+9"
			},
			"senses": [
				"visió de foscor 60 peus (pot veure criatures invisibles al mateix rang)"
			],
			"passive": 10,
			"resist": [
				"foc",
				"verí",
				{
					"resist": [
						"contundent",
						"perforant",
						"tallant"
					],
					"note": "d'atacs no màgics",
					"cond": true
				}
			],
			"conditionImmune": [
				"acovardit"
			],
			"idiomes": [
				"Comú",
				"Dracònic"
			],
			"cr": "16",
			"spellcasting": [
				{
					"name": "Llançament de conjurs Innat",
					"headerEntries": [
						"Arkhan's habilitat de llançament de conjurs is Carisma ({@dc 17} salvació de conjur). Ell pot llançar els següents encanteris, sentir que calguin components materials:"
					],
					"daily": {
						"3e": [
							"{@spell animar els morts}",
							"{@spell càstig marcador} (a 4t nivell)",
							"{@spell revifar}"
						],
						"1e": [
							"{@spell geas}",
							"{@spell llevar als morts}"
						]
					},
					"ability": "xa"
				}
			],
			"trait": [
				{
					"name": "Aura d'Odi",
					"entries": [
						"Tot i que l'Arkhan no és {@condition incapacitat}, ell i tots els diastres i morts morts a menys de 30 peus d'ell infligen 4 danys addicionals cada cop que xoquen amb un atac armat cos a cos (ja es tenen en compte en els atacs d'Arkhan). Aquest dany addicional és del mateix tipus que el tipus de dany de l'arma."
					]
				},
				{
					"name": "Mà de Vecna",
					"entries": [
						"La mà de Vecna ​​té 8 càrregues i recupera {@dices 1d4 + 4} càrregues gastades diàriament a l'alba. Arkhan pot llançar els conjurs següents des de la mà gastant el nombre especificat de càrregues ({@dc 18} salvació de conjur): {@spell dit de la mort} (5 càrregues), {@spell adormir} (1 càrrega), {@spell alentir} (2 càrrecs) i {@spell teleportació} (3 càrrecs)."
					]
				},
				{
					"name": "Equipament Especial",
					"entries": [
						"L'Arkhan porta {@item Fane-Eater|bgdia} i porta un vestit de {@item Obsidian Flint Dragon Plate|bgdia}. L'armadura dóna avantatge a l'Arkhan en les proves d'habilitat i en els tirs de salvació realitzats per evitar o acabar amb la condició {@condition grappled} sobre ell."
					]
				}
			],
			"action": [
				{
					"name": "Multiatac",
					"entries": [
						"Arkhan fa tres atacs amb armes."
					]
				},
				{
					"name": "Fane-Eater (Destral de batalla)",
					"entries": [
						"{@atk mw} {@hit 13} a impactar, 5 peus d'abast, un objectiu. {@h}16 ({@damage 1d8 + 12}) de dany tallant, o 17 ({@damage 1d10 + 12}) de dany tallant si s'usa amb dos mans, plus 9 ({@damage 2d8}) de dany de fred. Si l'objectiu és una criatura i l'Arkhan treu un 20 a la tirada d'atac, la criatura pren un 9 addicional ({@damage 2d8}) de dany necròtic, i Arkhan recupera una quantitat de punts de vida igual al dany necròtic infligit."
					]
				},
				{
					"name": "Javelina",
					"entries": [
						"{@atk mw,rw} {@hit 10} a impactar, 5 peus d'abast o 30/120 peus d'abast, un objectiu. {@h}8 ({@damage 1d6 + 5}) de dany perforant, mes 4 de dany perforant i 9 ({@damage 2d8}) de dany de fred si la javelina s'utilitzava per fer un atac cos a cos."
					]
				}
			],
			"hasToken": true,
			"senseTags": [
				"D"
			],
			"actionTags": [
				"Multiatac"
			],
			"languageTags": [
				"C",
				"DR"
			],
			"damageTags": [
				"C",
				"N",
				"P",
				"S"
			],
			"spellcastingTags": [
				"I"
			],
			"miscTags": [
				"MW",
				"RW",
				"THW"
			],
			"conditionInflictSpell": [
				"fascinat"
			],
			"hasFluff": true,
			"hasFluffImages": true
		},
		{
			"name": "Bel",
			"isNpc": true,
			"source": "BGDIA",
			"page": 115,
			"size": "L",
			"type": {
				"type": "infernal",
				"tags": [
					"discapacitat"
				]
			},
			"alineament": [
				"L",
				"E"
			],
			"ac": [
				{
					"ac": 19,
					"from": [
						"armadura natural"
					]
				}
			],
			"hp": {
				"average": 364,
				"formula": "27d10 + 216"
			},
			"speed": {
				"walk": 30,
				"volar": 60
			},
			"str": 28,
			"dex": 14,
			"con": 26,
			"int": 25,
			"wis": 19,
			"cha": 26,
			"save": {
				"dex": "+10",
				"con": "+16",
				"wis": "+12"
			},
			"skill": {
				"arcana": "+15",
				"deception": "+16",
				"insight": "+12",
				"persuasion": "+16"
			},
			"senses": [
				"visió veraç 120 peus"
			],
			"passive": 14,
			"resist": [
				"fred",
				{
					"resist": [
						"contundent",
						"perforant",
						"tallant"
					],
					"note": "d'atacs no màgics amb armes no platejades",
					"cond": true
				}
			],
			"immune": [
				"foc",
				"verí"
			],
			"conditionImmune": [
				"emmetzinat"
			],
			"idiomes": [
				"Comú",
				"Diàstric",
				"telepatia 120 peus"
			],
			"cr": "25",
			"spellcasting": [
				{
					"name": "Llançament de conjurs Innat",
					"headerEntries": [
						"Bel's habilitat de llançament de conjurs is Carisma ({@dc 23} salvació de conjur). Bel pot llançar els conjurs següents innatament (no requereixen materials):"
					],
					"will": [
						"{@spell detectar màgia}",
						"{@spell bola de foc}"
					],
					"daily": {
						"3e": [
							"{@spell dissipar màgia}",
							"{@spell immobilitzar criatura}",
							"{@spell imatge mirall}",
							"{@spell desconcertar}",
							"{@spell llevar als morts}",
							"{@spell teleportació}",
							"{@spell pare de foc}"
						],
						"1e": [
							"{@spell engarjolament}",
							"{@spell eixam de meteorits}"
						]
					},
					"ability": "xa"
				}
			],
			"trait": [
				{
					"name": "Aura de por",
					"entries": [
						"Qualsevol criatura hostil a Bel que comenci el seu torn a menys de 20 peus d'ell ha de salvar per Saviesa amb {@dc 23}, tret que Bel sigui {@condition incapacitat}. A menys que el desat tingui èxit, la criatura és {@condition acovardit} fins a l'inici del seu següent trencat. Si la tirada de salvació d'una criatura té èxit, la criatura és immune a l'aura de la por de Bel durant les 24 hores."
					]
				},
				{
					"name": "Resistència Llegendària (3/Dia)",
					"entries": [
						"Si Bel falla una tirada de salvació pot escollir superar-la."
					]
				},
				{
					"name": "Resistència a la Màgia",
					"entries": [
						"Bel té avantatge a salvar contra conjurs i altres efectes màgics."
					]
				},
				{
					"name": "Armament Màgic",
					"entries": [
						"Els atacs armats de Bel's són màgics."
					]
				}
			],
			"action": [
				{
					"name": "Multiatac",
					"entries": [
						"Bel fa tres atacs: dos amb la seva gran espasa i un amb la seva cua."
					]
				},
				{
					"name": "Espasa Gran",
					"entries": [
						"{@atk mw} {@hit 16} a impactar, 10 peus d'abast, un objectiu. {@h}23 ({@damage 4d6 + 9}) de dany tallant mes 21 ({@damage 6d6}) de dany de foc. Si l'objectiu és un objecte inflamable que no es subjecta ni es porta, s'encén."
					]
				},
				{
					"name": "Cua",
					"entries": [
						"{@atk mw} {@hit 16} a impactar, 10 peus d'abast, un objectiu. {@h}25 ({@damage 3d10 + 9}) de dany contundent. If the target is a creature, ha de salvar per Constitució amb {@dc 23} or be {@condition atordit} fins el final del seu proper torn."
					]
				}
			],
			"legendary": [
				{
					"name": "Bola de Foc",
					"entries": [
						"Bel llança una bola de foc."
					]
				},
				{
					"name": "Tactical Edge (Costa 2 Accions)",
					"entries": [
						"Tira un {@dau d6} per a Bel. El nombre llançat al dau es resta de la següent tirada d'atac contra Bel o un aliat de la seva elecció durant el minut següent."
					]
				},
				{
					"name": "Summon Ice Devil (Costa 3 Accions)",
					"entries": [
						"Bel convoca màgicament un diable de gel amb una llança de gel (tal com es descriu a l'entrada del diable de gel al Manual del monstre). El diable de gel apareix en un espai desocupat a 60 peus de Bel, actua com a aliat de Bel i pot convocar altres diables si té aquest poder. El diable de gel roman fins que Bel mor o fins que ho descarta com una acció."
					]
				}
			],
			"hasToken": true,
			"traitTags": [
				"Resistències Llegendàries",
				"Resistència a la Màgia",
				"Armament Màgic"
			],
			"senseTags": [
				"U"
			],
			"actionTags": [
				"Multiatac"
			],
			"languageTags": [
				"C",
				"I"
			],
			"damageTags": [
				"B",
				"F",
				"S"
			],
			"spellcastingTags": [
				"I"
			],
			"miscTags": [
				"MW",
				"RCH"
			],
			"conditionInflict": [
				"acovardit",
				"atordit"
			],
			"conditionInflictSpell": [
				"encegat",
				"eixordat",
				"invisible",
				"paralitzat",
				"retingut"
			],
			"hasFluff": true,
			"hasFluffImages": true
		},
		{
			"name": "Alè Amarg",
			"isNpc": true,
			"source": "BGDIA",
			"page": 90,
			"_copy": {
				"name": "Diable Banyut",
				"source": "MM",
				"_mod": {
					"*": {
						"mode": "substituirTxt",
						"replace": "el diable",
						"with": "Alè Amarg",
						"flags": "i"
					}
				}
			},
			"speed": {
				"walk": 20
			},
			"hasToken": true
		},
		{
			"name": "Guant Negre de la Perdició",
			"source": "BGDIA",
			"page": 235,
			"size": "M",
			"type": {
				"type": "humanoide",
				"tags": [
					"humà"
				]
			},
			"alineament": [
				"L",
				"E"
			],
			"ac": [
				{
					"ac": 16,
					"from": [
						"{@item cota de malla|phb}"
					]
				}
			],
			"hp": {
				"average": 51,
				"formula": "6d8 + 24"
			},
			"speed": {
				"walk": 30
			},
			"str": 18,
			"dex": 11,
			"con": 18,
			"int": 12,
			"wis": 15,
			"cha": 18,
			"save": {
				"wis": "+5"
			},
			"skill": {
				"intimidation": "+7",
				"perception": "+5"
			},
			"passive": 15,
			"conditionImmune": [
				"acovardit"
			],
			"idiomes": [
				"Comú"
			],
			"cr": "6",
			"spellcasting": [
				{
					"name": "Llançament de Conjurs",
					"headerEntries": [
						"The black gauntlet és llançador/a de conjurs de nivell 5. La seva habilitat de llançament de conjurs és Carisma (CD per salvar conjur {@dc 15}, {@hit 7} a impactar amb atacs màgics). Té els següents conjurs de clergue preparats:"
					],
					"spells": {
						"0": {
							"spells": [
								"{@spell guia}",
								"{@spell flama sagrada}",
								"{@spell taumatúrgia}"
							]
						},
						"1": {
							"slots": 4,
							"spells": [
								"{@spell perdició}",
								"{@spell beneir}",
								"{@spell curar ferides}",
								"{@spell sageta guia} (vegeu \"Accions\" a continuació)"
							]
						},
						"2": {
							"slots": 3,
							"spells": [
								"{@spell ceguera/sordera}",
								"{@spell immobilitzar humanoide}",
								"{@spell silenci}"
							]
						},
						"3": {
							"slots": 2,
							"spells": [
								"{@spell encàrrec}",
								"{@spell guardians espirituals}"
							]
						}
					},
					"ability": "xa"
				}
			],
			"trait": [
				{
					"name": "Aura de terror",
					"entries": [
						"Quan una criatura hostil a 5 peus del guant negre fa una tirada d'atac o una tirada de salvació, té desavantatge a la tirada. Les criatures que són immunes a la condició {@condition acovardit} són immunes a aquest tret."
					]
				},
				{
					"name": "Disciplina tàctica",
					"entries": [
						"El guant negre té avantatge en totes les proves d'habilitat i en els tirs de salvació realitzats durant el combat."
					]
				}
			],
			"action": [
				{
					"name": "Multiatac",
					"entries": [
						"El guant negre fa dos atacs amb la seva maça."
					]
				},
				{
					"name": "Maça",
					"entries": [
						"{@atk mw} {@hit 7} a impactar, 5 peus d'abast, un objectiu. {@h}7 ({@damage 1d6 + 4}) de dany contundent mes 13 ({@damage 3d8}) de dany necròtic."
					]
				},
				{
					"name": "Sageta Guia (Encanteri de 1r nivell; Requereix un espai per a encanteris)",
					"entries": [
						"{@atk rs} {@hit 7} a impactar, 120 peus d'abast, una criatura. {@h}14 ({@damage 4d6}) de dany radiant, i la següent tirada d'atac feta contra l'objectiu abans del final del següent torn del guant negre té avantatge. Si el guant negre llança aquest encanteri utilitzant una ranura d'encanteri de 2n nivell o superior, el dany incrementa en {@dice 1d6} per cada nivell per sobre d'1."
					]
				}
			],
			"hasToken": true,
			"actionTags": [
				"Multiatac"
			],
			"languageTags": [
				"C"
			],
			"damageTags": [
				"B",
				"N",
				"R"
			],
			"spellcastingTags": [
				"CC"
			],
			"miscTags": [
				"MW"
			],
			"conditionInflictSpell": [
				"encegat",
				"eixordat",
				"paralitzat"
			],
			"hasFluff": true
		},
		{
			"name": "Buc d'os",
			"source": "BGDIA",
			"page": 119,
			"size": "L",
			"type": "monstrositat",
			"alineament": [
				"U"
			],
			"ac": [
				{
					"ac": 12,
					"from": [
						"armadura natural"
					]
				}
			],
			"hp": {
				"average": 27,
				"formula": "5d10"
			},
			"speed": {
				"walk": 15,
				"climb": 15
			},
			"str": 10,
			"dex": 5,
			"con": 11,
			"int": 6,
			"wis": 9,
			"cha": 3,
			"senses": [
				"visió de foscor 60 peus"
			],
			"passive": 9,
			"cr": "1/4",
			"trait": [
				{
					"name": "Adhesiu",
					"entries": [
						"El comiat d'os pot fer que s'hi adhereixin objectes mitjans o més petits. Una criatura mitjana o més petita que toca el bucc d'os és {@condition grappled} per ella ({@dc 10} per escapar)."
					]
				},
				{
					"name": "Crit de la mort",
					"entries": [
						"Quan el bucc d'os mor, emet un crit de sang que es pot escoltar a una distància de 120 peus. Aquest crit fa que el material orgànic i no màgic es podrigui a 10 peus de l'os. Cada criatura a menys de 10 peus del bucc ossi quan mor triga 9 ({@damage 2d8}) de dany necròtic."
					]
				},
				{
					"name": "Grimpat d'Aranya",
					"entries": [
						"The bone whelk pot escalar superfícies difícils (incloent cap per avall pels sostres) sense haver de fer una tirada d'habilitat."
					]
				}
			],
			"action": [
				{
					"name": "Mossegada",
					"entries": [
						"{@atk mw} {@hit 2} a impactar, 5 peus d'abast, una criatura. {@h}4 ({@damage 1d8}) de dany perforant."
					]
				}
			],
			"hasToken": true,
			"traitTags": [
				"Grimpat d'Aranya"
			],
			"senseTags": [
				"D"
			],
			"damageTags": [
				"N",
				"P"
			],
			"miscTags": [
				"MW"
			],
			"hasFluff": true,
			"hasFluffImages": true
		},
		{
			"name": "Burney el barber",
			"isNpc": true,
			"isNamedCreature": true,
			"source": "BGDIA",
			"page": 129,
			"_copy": {
				"name": "Drac de Coure Ancià",
				"source": "MM",
				"_mod": {
					"*": {
						"mode": "substituirTxt",
						"replace": "el drac",
						"with": "Burney",
						"flags": "i"
					},
					"trait": {
						"mode": "appendArr",
						"items": [
							{
								"name": "Sanador",
								"entries": [
									"Burney té els avantatges de la proesa {@feat healer}, així com la competència tant amb el {@item healer's kit|phb} com amb el {@item herbalism kit|phb}."
								]
							},
							{
								"name": "Les benediccions de Bahamut",
								"entries": [
									"Burney ha rebut diverses benediccions en el seu servei a Bahamut:",
									{
										"type": "llista",
										"items": [
											"A menys que Burney decideixi el contrari, una vegada que qualsevol criatura menys poderosa que una deïtat ha fet tres passos d'ella, ja no la poden recordar ni haver interactuat amb ella específicament.",
											"Burney està sota l'efecte d'un encanteri permanent {@spell ment en blanc} i no es pot detectar per mitjans màgics o mundans tret que ella ho desitgi. A canvi d'aquesta benedicció, Burney no pot prendre cap acció directa contra els habitants dels Nou Inferns, tot i que certament pot comptar amb l'ajuda d'aquells que puguin.",
											"Burney sempre sap la ubicació del Wandering Emporium i pot transportar-s'hi com si fes un encanteri {@spell formular el retorn}. Això explica per què Burney sembla simplement aparèixer enmig del mercat completament desplegat cada matí que està actiu per oferir servei i explicar històries.",
											"Un cop al dia, quan Burney així ho desitgi, pot transportar-se instantàniament a la cort de Bahamut mitjançant una poderosa benedicció semblant a l'encanteri {@spell saltar de pla}."
										]
									}
								]
							}
						]
					}
				}
			},
			"hasToken": true
		},
		{
			"name": "Chukka",
			"isNpc": true,
			"source": "BGDIA",
			"page": 83,
			"_copy": {
				"name": "Kenku",
				"source": "MM",
				"_mod": {
					"*": {
						"mode": "substituirTxt",
						"replace": "el kenku",
						"with": "Chukka",
						"flags": "i"
					}
				}
			},
			"action": [
				{
					"name": "Lluç platejat",
					"entries": [
						"{@atk mw} {@hit 2} a impactar, 5 peus d'abast, un objectiu. {@h}5 ({@damage 1d10}) de dany perforant."
					]
				}
			],
			"hasToken": true,
			"miscTags": [
				"MW"
			]
		},
		{
			"name": "Clonk",
			"isNpc": true,
			"source": "BGDIA",
			"page": 83,
			"_copy": {
				"name": "Kenku",
				"source": "MM",
				"_mod": {
					"*": {
						"mode": "substituirTxt",
						"replace": "el kenku",
						"with": "Clonk",
						"flags": "i"
					}
				}
			},
			"action": [
				{
					"name": "Fofferni Warhammer",
					"entries": [
						"{@atk mw} {@hit 2} a impactar, 5 peus d'abast, un objectiu. {@h}4 ({@damage 1d8}) de dany contundent, o 5 ({@damage 1d10 + 1}) de dany contundent si s'usa a dues mans per un atac cos a cos."
					]
				}
			],
			"hasToken": true,
			"damageTags": [
				"B"
			],
			"miscTags": [
				"MW"
			]
		},
		{
			"name": "Crokek'toeck",
			"isNpc": true,
			"source": "BGDIA",
			"page": 231,
			"size": "G",
			"type": {
				"type": "infernal",
				"tags": [
					"dimoni"
				]
			},
			"alineament": [
				"C",
				"E"
			],
			"ac": [
				{
					"ac": 15,
					"from": [
						"armadura natural"
					]
				}
			],
			"hp": {
				"average": 297,
				"formula": "17d20 + 119"
			},
			"speed": {
				"walk": 60,
				"swim": 60
			},
			"str": 28,
			"dex": 10,
			"con": 24,
			"int": 6,
			"wis": 10,
			"cha": 13,
			"save": {
				"con": "+12",
				"wis": "+5"
			},
			"senses": [
				"visió de foscor 120 peus"
			],
			"passive": 10,
			"resist": [
				"fred",
				"foc",
				"elèctric",
				{
					"resist": [
						"contundent",
						"perforant",
						"tallant"
					],
					"note": "d'atacs no màgics",
					"cond": true
				}
			],
			"immune": [
				"verí"
			],
			"conditionImmune": [
				"fascinat",
				"acovardit",
				"emmetzinat"
			],
			"idiomes": [
				"entén Abyssal però no pot parlar"
			],
			"cr": "14",
			"trait": [
				{
					"name": "Amfibi",
					"entries": [
						"Crokek'toeck pot respirar aire i a l'aigua"
					]
				},
				{
					"name": "Resistència a la Màgia",
					"entries": [
						"Crokek'toeck té avantatge a salvar contra conjurs i altres efectes màgics."
					]
				},
				{
					"name": "Armament Màgic",
					"entries": [
						"Els atacs armats de Crokek'toeck's són màgics."
					]
				},
				{
					"name": "Memòria segura",
					"entries": [
						"Crokek'toeck és immune a les aigües del riu Styx, així com a qualsevol efecte que pugui robar o modificar els seus records o detectar o llegir els seus pensaments."
					]
				},
				{
					"name": "Salt Dempeus",
					"entries": [
						"Crokek'toeck pot arribar a saltar 60 peus de longitud i 30 peus d'alçada. no li cal agafar embranzida."
					]
				}
			],
			"action": [
				{
					"name": "Mossegada",
					"entries": [
						"{@atk mw} {@hit 14} a impactar, 15 peus d'abast, un objectiu. {@h}44 ({@damage 10d6 + 9}) de dany perforant."
					]
				},
				{
					"name": "Desboca els aliats {@recharge}",
					"entries": [
						"Crokek'toeck obre la boca i degolla {@dice 1d4} {@creature barlgura||barlguras}, {@dice 3d6} {@creature gnoll||gnolls} dirigit per 1 {@creature gnoll fang de Yeenoghu}, {@dices 6d6} {@creature dretch||dretches}, o {@dice 1d3} {@creature vrock||vrocks}. Cada criatura que desgorge apareix en un espai desocupat a 30 peus de la boca de Crokek'toeck, o el següent espai desocupat més proper."
					]
				}
			],
			"hasToken": true,
			"traitTags": [
				"Amfibi",
				"Resistència a la Màgia",
				"Armament Màgic"
			],
			"senseTags": [
				"SD"
			],
			"languageTags": [
				"AB",
				"CS"
			],
			"damageTags": [
				"P"
			],
			"miscTags": [
				"MW",
				"RCH"
			],
			"hasFluff": true,
			"hasFluffImages": true
		},
		{
			"name": "Cap de la mort de Bhaal",
			"source": "BGDIA",
			"page": 233,
			"size": "M",
			"type": {
				"type": "humanoide",
				"tags": [
					"humà"
				]
			},
			"alineament": [
				"C",
				"E"
			],
			"ac": [
				15
			],
			"hp": {
				"average": 76,
				"formula": "8d8 + 40"
			},
			"speed": {
				"walk": 50
			},
			"str": 20,
			"dex": 20,
			"con": 20,
			"int": 14,
			"wis": 13,
			"cha": 16,
			"skill": {
				"intimidation": "+6",
				"perception": "+4",
				"persuasion": "+6",
				"stealth": "+11"
			},
			"senses": [
				"visió de foscor 60 peus"
			],
			"passive": 14,
			"idiomes": [
				"Comú"
			],
			"cr": "5",
			"trait": [
				{
					"name": "Aura d'assassinat",
					"entries": [
						"Mentre el cap de la mort no sigui {@condition incapacitat}, les criatures hostils a menys de 5 peus d'ella guanyen vulnerabilitat a danys perforants tret que tinguin resistència o immunitat a aquests danys."
					]
				},
				{
					"name": "Resistència a la Màgia",
					"entries": [
						"The death's head té avantatge a salvar contra conjurs i altres efectes màgics."
					]
				}
			],
			"action": [
				{
					"name": "Multiatac",
					"entries": [
						"El cap de la mort utilitza Stunning Gaze i fa dos atacs de punyal."
					]
				},
				{
					"name": "Daga",
					"entries": [
						"{@atk mw,rw} {@hit 7} a impactar, 5 peus d'abast o 20/60 peus d'abast, un objectiu. {@h}7 ({@damage 1d4 + 5}) de dany perforant."
					]
				},
				{
					"name": "Mirada impressionant",
					"entries": [
						"El cap de la mort apunta a una criatura que pot veure a 30 peus d'ella. The target ha de salvar per Saviesa amb {@dc 14} or be {@condition atordit} fins el final del seu proper torn."
					]
				}
			],
			"reaction": [
				{
					"name": "Imparable (3/dia)",
					"entries": [
						"El cap de la mort redueix a 0 el dany que pren d'un atac."
					]
				}
			],
			"hasToken": true,
			"traitTags": [
				"Resistència a la Màgia"
			],
			"senseTags": [
				"D"
			],
			"actionTags": [
				"Multiatac"
			],
			"languageTags": [
				"C"
			],
			"damageTags": [
				"P"
			],
			"miscTags": [
				"MW",
				"RW",
				"THW"
			],
			"conditionInflict": [
				"atordit"
			],
			"hasFluff": true
		},
		{
			"name": "Esperit Dríade",
			"source": "BGDIA",
			"page": 108,
			"_copy": {
				"name": "Banshee",
				"source": "MM",
				"_mod": {
					"*": {
						"mode": "substituirTxt",
						"replace": "banshee",
						"with": "dríade"
					}
				}
			},
			"hasToken": true
		},
		{
			"name": "Duc Thalamra Vanthampur",
			"isNpc": true,
			"source": "BGDIA",
			"page": 38,
			"size": "M",
			"type": {
				"type": "humanoide",
				"tags": [
					"humà"
				]
			},
			"alineament": [
				"L",
				"E"
			],
			"ac": [
				10
			],
			"hp": {
				"average": 78,
				"formula": "12d8 + 24"
			},
			"speed": {
				"walk": 30
			},
			"str": 17,
			"dex": 10,
			"con": 15,
			"int": 13,
			"wis": 16,
			"cha": 18,
			"skill": {
				"deception": "+6",
				"insight": "+5",
				"intimidation": "+6",
				"religion": "+3"
			},
			"senses": [
				"visió de foscor 120 peus (see ulls de diables below)"
			],
			"passive": 13,
			"idiomes": [
				"Comú",
				"Diàstric"
			],
			"cr": "4",
			"trait": [
				{
					"name": "Devoció fosca",
					"entries": [
						"Thalamra té avantatge a salvar contra ser {@condition fascinat} o {@condition acovardit}."
					]
				},
				{
					"name": "Ulls de Diables",
					"entries": [
						"Thalamra pot veure normalment a la foscor, tant màgica com no màgica, fora d'un 120 peus d'abast."
					]
				}
			],
			"action": [
				{
					"name": "Multiatac",
					"entries": [
						"Thalamra utilitza missil èldritx dues vegades o fa dos atacs desarmats."
					]
				},
				{
					"name": "Missil Èldritx (Truc)",
					"entries": [
						"{@atk rs} {@hit 6} a impactar, 120 peus d'abast, una criatura. {@h}9 ({@damage 1d10 + 4}) de dany de força."
					]
				},
				{
					"name": "Atac Desarmat",
					"entries": [
						"{@atk mw} {@hit 5} a impactar, 5 peus d'abast, un objectiu. {@h}4 dany contundent."
					]
				}
			],
			"reaction": [
				{
					"name": "Venjança dels Inferns (Conjur de Nivell 1; 2/Dia)",
					"entries": [
						"Quan Thalamra és danyada per una criatura a menys de 60 peus d'ella que pot veure, la criatura que la va danyar queda envoltada en flames infernals i ha de salvar per Destresa amb {@dc 14}. Qui falli rep 16 (@damage 3d10}) de dany de foc; qui superi, en rep la meitat."
					]
				}
			],
			"hasToken": true,
			"traitTags": [
				"Ulls de Diables"
			],
			"senseTags": [
				"SD"
			],
			"actionTags": [
				"Multiatac"
			],
			"languageTags": [
				"C",
				"I"
			],
			"damageTags": [
				"B",
				"F",
				"O"
			],
			"miscTags": [
				"MW"
			],
			"hasFluff": true,
			"hasFluffImages": true
		},
		{
			"name": "Elliach",
			"isNpc": true,
			"source": "BGDIA",
			"page": 130,
			"_copy": {
				"name": "Mag",
				"source": "MM",
				"_mod": {
					"*": {
						"mode": "substituirTxt",
						"replace": "el mag",
						"with": "Elliach",
						"flags": "i"
					}
				}
			},
			"type": {
				"type": "humanoide",
				"tags": [
					"humà"
				]
			},
			"alineament": [
				"L",
				"E"
			],
			"action": [
				{
					"name": "Daga",
					"entries": [
						"{@atk mw,rw} {@hit 5} a impactar, 10 peus d'abast o 20/60 peus d'abast, un objectiu. {@h}4 ({@damage 1d4 + 2}) de dany perforant."
					]
				}
			],
			"hasToken": true,
			"miscTags": [
				"MW",
				"RCH",
				"RW",
				"THW"
			]
		},
		{
			"name": "Feonor",
			"isNpc": true,
			"source": "BGDIA",
			"page": 130,
			"_copy": {
				"name": "Archimat",
				"source": "MM",
				"_mod": {
					"*": {
						"mode": "substituirTxt",
						"replace": "l'arximag",
						"with": "Feonor",
						"flags": "i"
					}
				}
			},
			"type": {
				"type": "humanoide",
				"tags": [
					"humà"
				]
			},
			"alineament": [
				"N",
				"E"
			],
			"hasToken": true
		},
		{
			"name": "Fiendish Flesh Gòlem",
			"source": "BGDIA",
			"page": 236,
			"size": "L",
			"type": "construir",
			"alineament": [
				"U"
			],
			"ac": [
				{
					"ac": 12,
					"from": [
						"armadura natural"
					]
				}
			],
			"hp": {
				"average": 210,
				"formula": "20d10 + 100"
			},
			"speed": {
				"walk": 30,
				"volar": {
					"number": 30,
					"condition": "(flotar)"
				},
				"canHover": true
			},
			"str": 20,
			"dex": 9,
			"con": 20,
			"int": 7,
			"wis": 10,
			"cha": 5,
			"senses": [
				"visió de foscor 60 peus"
			],
			"passive": 10,
			"resist": [
				"fred",
				"foc"
			],
			"immune": [
				"elèctric",
				"verí",
				{
					"immune": [
						"contundent",
						"perforant",
						"tallant"
					],
					"note": "d'atacs no màgics que no són adamantins ni platejats",
					"cond": true
				}
			],
			"conditionImmune": [
				"fascinat",
				"escapament",
				"acovardit",
				"paralitzat",
				"petrificat",
				"emmetzinat"
			],
			"idiomes": [
				"comprèn els idiomes dels seus creadors però no pot parlar"
			],
			"cr": "8",
			"trait": [
				{
					"name": "Bersèrk",
					"entries": [
						"Quan el gòlem comenci el seu torn amb 100 punts de vida o menys, tira {@dice d6}. Si surt un 6 el gòlem és torna bersèrk. A cada torn així ataca a la criatura que tingui més a prop i pugui veure. Si no n'hi ha cap prou a prop per moure's i atacar-la, atacarà a un objecte (preferent més petit). Quan el gòlem sigui bersèrk no parara fins que sigui destruit o recuperi tots els punts de vida.",
						"Si el creador del gòlem hi és a 60 peus d'abast pot intentar calmar-lo com a acció. El gòlem l'ha de poder sentir. El creador farà una tirada de Carisma (Persuasión) amb {@dc 15}. Si supera, el bersèrk s'acaba pel gòlem. Si el gòlem torna a rebre mal estant a 100 punts de vida o menys, pot tornar a activar-se el bersèrk."
					]
				},
				{
					"name": "Forma immutable",
					"entries": [
						"The gòlem és immune a tot conjur o efecte que vulgui alterar-li la forma."
					]
				},
				{
					"name": "Absorbir Electricitat",
					"entries": [
						"Quan el gòlem hagi de rebre dany elèctric, no rep mal sinò que recupera la meitat de dany elèctric en punts de vida."
					]
				},
				{
					"name": "Resistència a la Màgia",
					"entries": [
						"The gòlem té avantatge a salvar contra conjurs i altres efectes màgics."
					]
				},
				{
					"name": "Armament Màgic",
					"entries": [
						"Els atacs armats de The gòlem's són màgics."
					]
				}
			],
			"action": [
				{
					"name": "Multiatac",
					"entries": [
						"El gòlem fa dos atacs de slam."
					]
				},
				{
					"name": "Colpeig",
					"entries": [
						"{@atk mw} {@hit 8} a impactar, 5 peus d'abast, un objectiu. {@h}16 ({@damage 2d10 + 5}) de dany contundent."
					]
				}
			],
			"hasToken": true,
			"traitTags": [
				"Absorbir Dany",
				"Forma immutable",
				"Resistència a la Màgia",
				"Armament Màgic"
			],
			"senseTags": [
				"D"
			],
			"actionTags": [
				"Multiatac"
			],
			"languageTags": [
				"CS"
			],
			"damageTags": [
				"B"
			],
			"miscTags": [
				"MW"
			],
			"hasFluff": true
		},
		{
			"name": "Puny de Perdició",
			"source": "BGDIA",
			"page": 232,
			"size": "M",
			"type": {
				"type": "humanoide",
				"tags": [
					"humà"
				]
			},
			"alineament": [
				"L",
				"E"
			],
			"ac": [
				{
					"ac": 18,
					"from": [
						"{@item cota de malla|phb}",
						"{@item shield|phb}"
					]
				}
			],
			"hp": {
				"average": 22,
				"formula": "4d8 + 4"
			},
			"speed": {
				"walk": 30
			},
			"str": 16,
			"dex": 11,
			"con": 13,
			"int": 10,
			"wis": 12,
			"cha": 11,
			"passive": 11,
			"conditionImmune": [
				"acovardit"
			],
			"idiomes": [
				"Comú"
			],
			"cr": "1/2",
			"trait": [
				{
					"name": "Disciplina tàctica",
					"entries": [
						"El puny de Bane té avantatge en totes les proves d'habilitat i en els tirs de salvació realitzats durant el combat."
					]
				}
			],
			"action": [
				{
					"name": "Maça",
					"entries": [
						"{@atk mw} {@hit 5} a impactar, 5 peus d'abast, un objectiu. {@h}6 ({@damage 1d6 + 3}) de dany contundent."
					]
				},
				{
					"name": "Arc llarg",
					"entries": [
						"{@atk rw} {@hit 2} a impactar, 150/600 peus d'abast, un objectiu. {@h}4 ({@damage 1d8}) de dany perforant."
					]
				}
			],
			"hasToken": true,
			"languageTags": [
				"C"
			],
			"damageTags": [
				"B",
				"P"
			],
			"miscTags": [
				"MW",
				"RNG",
				"RW"
			],
			"hasFluff": true
		},
		{
			"name": "Daga voladora",
			"source": "BGDIA",
			"page": 30,
			"_copy": {
				"name": "Espasa Voladora",
				"source": "MM",
				"_mod": {
					"*": {
						"mode": "substituirTxt",
						"replace": "espasa",
						"with": "daga"
					},
					"action": {
						"mode": "substituirArr",
						"replace": "Espasa llarga",
						"items": {
							"name": "Daga",
							"entries": [
								"{@atk mw} {@hit 3} a impactar, 5 peus d'abast, un objectiu. {@h}3 ({@damage 1d4 + 1}) de dany perforant."
							]
						}
					}
				}
			},
			"size": "T",
			"hp": {
				"average": 7,
				"formula": "3d4"
			},
			"hasToken": true,
			"damageTags": [
				"P"
			]
		},
		{
			"name": "Gideon Lightward",
			"isNpc": true,
			"source": "BGDIA",
			"page": 65,
			"size": "M",
			"type": "no mort",
			"alineament": [
				"L",
				"E"
			],
			"ac": [
				11
			],
			"hp": {
				"average": 136,
				"formula": "16d8 + 64"
			},
			"speed": {
				"walk": 30
			},
			"str": 18,
			"dex": 13,
			"con": 18,
			"int": 10,
			"wis": 18,
			"cha": 13,
			"save": {
				"dex": "+4",
				"con": "+7",
				"wis": "+7"
			},
			"skill": {
				"insight": "+7",
				"religion": "+6"
			},
			"senses": [
				"visió de foscor 60 peus"
			],
			"passive": 14,
			"resist": [
				{
					"resist": [
						"contundent",
						"perforant",
						"tallant"
					],
					"note": "d'atacs no màgics",
					"cond": true
				}
			],
			"immune": [
				"necròtic",
				"verí"
			],
			"vulnerable": [
				"radiant"
			],
			"conditionImmune": [
				"escapament",
				"paralitzat",
				"emmetzinat"
			],
			"idiomes": [
				"Comú"
			],
			"cr": "6",
			"trait": [
				{
					"name": "Regeneració",
					"entries": [
						"Gideon recupera 10 punts de vida a l'inici de cada torn seu. Si rep dany radiant, aquest tret no funciona al començament del seu següent torn. Gideon és destruït només si comença el seu torn amb 0 punts de vida i no es regenera."
					]
				}
			],
			"action": [
				{
					"name": "Multiatac",
					"entries": [
						"Gideon ataca dues vegades amb els punys."
					]
				},
				{
					"name": "Puny",
					"entries": [
						"{@atk mw} {@hit 7} a impactar, 5 peus d'abast, un objectiu. {@h}11 ({@damage 2d6 + 4}) de dany contundent."
					]
				},
				{
					"name": "Mirada marchita",
					"entries": [
						"Gideon apunta a una criatura que pot veure a 60 peus d'ell. L'objectiu ha de salvar per Constitució amb {@dc 15}. Qui falli rep 22 (@damage 4d10}) de dany necròtic; qui superi, en rep la meitat."
					]
				}
			],
			"hasToken": true,
			"traitTags": [
				"Regeneració"
			],
			"senseTags": [
				"D"
			],
			"actionTags": [
				"Multiatac"
			],
			"languageTags": [
				"C"
			],
			"damageTags": [
				"B",
				"N"
			],
			"miscTags": [
				"MW"
			],
			"hasFluff": true,
			"hasFluffImages": true
		},
		{
			"name": "Harkina Hunt",
			"isNpc": true,
			"source": "BGDIA",
			"page": 53,
			"_copy": {
				"name": "Plebeu",
				"source": "MM",
				"_mod": {
					"action": {
						"mode": "appendArr",
						"items": {
							"name": "Arc llarg",
							"entries": [
								"{@atk mw} {@hit 2} a impactar, 5 peus d'abast, un objectiu. {@h}4 ({@damage 1d8}) de dany perforant."
							]
						}
					}
				}
			},
			"type": {
				"type": "humanoide",
				"tags": [
					"humà"
				]
			},
			"hasToken": true,
			"damageTags": [
				"B",
				"P"
			],
			"miscTags": [
				"MW",
				"RNG"
			]
		},
		{
			"name": "Hellwasp",
			"source": "BGDIA",
			"page": 236,
			"size": "L",
			"type": "infernal",
			"alineament": [
				"L",
				"E"
			],
			"ac": [
				{
					"ac": 19,
					"from": [
						"armadura natural"
					]
				}
			],
			"hp": {
				"average": 52,
				"formula": "8d10 + 8"
			},
			"speed": {
				"walk": 10,
				"volar": {
					"number": 60,
					"condition": "(flotar)"
				},
				"canHover": true
			},
			"str": 18,
			"dex": 15,
			"con": 12,
			"int": 10,
			"wis": 10,
			"cha": 7,
			"save": {
				"dex": "+5",
				"wis": "+3"
			},
			"senses": [
				"visió de foscor 60 peus"
			],
			"passive": 10,
			"immune": [
				"foc"
			],
			"vulnerable": [
				"fred"
			],
			"idiomes": [
				"Diàstric",
				"telepatía 300 peus (només amb altres hellwasps)"
			],
			"cr": "5",
			"trait": [
				{
					"name": "Armament Màgic",
					"entries": [
						"Els atacs armats de The hellwasp's són màgics."
					]
				}
			],
			"action": [
				{
					"name": "Multiatac",
					"entries": [
						"L'infern fa dos atacs: un amb el seu agulló i un altre amb les seves urpes d'espasa."
					]
				},
				{
					"name": "Fiblar",
					"entries": [
						"{@atk mw} {@hit 7} a impactar, 5 peus d'abast, una criatura. {@h}8 ({@damage 1d8 + 4}) de dany perforant mes 7 ({@damage 2d6}) de dany de foc, i l'objectiu ha de superar una salvada de Constitució amb {@dc 12} o estar {@condition emmetzinat} durant 1 minut. Si bé {@condition emmetzinat} d'aquesta manera, l'objectiu també és {@condition paralitzat}. L'objectiu pot repetir la salvada al final de cada torn el seu, acabant l'efecte prematurament si supera."
					]
				},
				{
					"name": "Garres d'espasa",
					"entries": [
						"{@atk mw} {@hit 7} a impactar, 5 peus d'abast, un objectiu. {@h}11 ({@damage 2d6 + 4}) de dany perforant."
					]
				}
			],
			"hasToken": true,
			"traitTags": [
				"Armament Màgic"
			],
			"senseTags": [
				"D"
			],
			"actionTags": [
				"Multiatac"
			],
			"languageTags": [
				"I",
				"TP"
			],
			"damageTags": [
				"F",
				"P"
			],
			"miscTags": [
				"MW"
			],
			"conditionInflict": [
				"paralitzat",
				"emmetzinat"
			],
			"hasFluff": true,
			"hasFluffImages": true
		},
		{
			"name": "Larva Hellwasp",
			"source": "BGDIA",
			"page": 95,
			"_copy": {
				"name": "Centpeus gegant",
				"source": "MM"
			},
			"hasToken": true
		},
		{
			"name": "Hollyphant",
			"source": "BGDIA",
			"page": 237,
			"size": "S",
			"type": "celestial",
			"alineament": [
				"L",
				"G"
			],
			"ac": [
				{
					"ac": 18,
					"from": [
						"armadura natural"
					]
				}
			],
			"hp": {
				"average": 36,
				"formula": "8d6 + 8"
			},
			"speed": {
				"walk": 20,
				"volar": 120
			},
			"str": 10,
			"dex": 11,
			"con": 12,
			"int": 16,
			"wis": 19,
			"cha": 16,
			"save": {
				"dex": "+3",
				"con": "+4",
				"cha": "+6"
			},
			"passive": 14,
			"resist": [
				{
					"resist": [
						"contundent",
						"perforant",
						"tallant"
					],
					"note": "d'atacs no màgics",
					"cond": true
				}
			],
			"immune": [
				"verí"
			],
			"conditionImmune": [
				"emmetzinat"
			],
			"idiomes": [
				"Celestial",
				"telepatia 120 peus"
			],
			"cr": "5",
			"spellcasting": [
				{
					"name": "Llançament de conjurs Innat",
					"headerEntries": [
						"L'habilitat de llançament de conjurs innata de The hollyphant és Saviesa ({@dc 15} salvació de conjur). Pot llançar els conjurs següents innatament (no necessiten components materials):"
					],
					"will": [
						"{@spell llum}"
					],
					"daily": {
						"2e": [
							"{@spell beneir}",
							"{@spell curar ferides}",
							"{@spell protegir del bé i del mal}"
						],
						"1e": [
							"{@spell desterrament}",
							"{@spell sanar}",
							"{@spell llevar als morts}",
							"{@spell canviaformes} (en un {@creature mamut} de pell daurada amb ales emplomades i una velocitat de vol de 120 peus)",
							"{@spell teleportació} (sense possibilitat d'error)"
						]
					},
					"ability": "sabia"
				}
			],
			"trait": [
				{
					"name": "Aura d'invulnerabilitat",
					"entries": [
						"Una aura {@condition invisible} forma una esfera de 10 peus de radi al voltant del grèvol durant el temps que viu. Qualsevol encanteri de 5è nivell o inferior llançat des de fora de la barrera no pot afectar les criatures o els objectes que hi ha dins, fins i tot si l'encanteri es llança amb un espai de conjur de nivell superior. Aquest encanteri pot apuntar a criatures i objectes dins de la barrera, però l'encanteri no té cap efecte sobre ells. De la mateixa manera, l'àrea dins de la barrera queda exclosa de les zones afectades per aquests encanteris. El grèvol pot fer servir una acció per suprimir aquest tret fins que acabi la seva concentració (com si es concentrés en un encanteri)."
					]
				},
				{
					"name": "Armament Màgic",
					"entries": [
						"Els atacs armats de The hollyphant's són màgics."
					]
				}
			],
			"action": [
				{
					"name": "Ullals",
					"entries": [
						"{@atk mw} {@hit 3} a impactar, 5 peus d'abast, un objectiu. {@h}3 ({@damage 1d6}) de dany perforant."
					]
				},
				{
					"name": "Trompeta (3/dia)",
					"entries": [
						"El grèvol bufa aire a través del seu tronc, creant un so de trompeta que es pot escoltar a una distància de 600 peus. La trompeta també crea un con d'energia de 30 peus que té un dels efectes següents, escollit pel grèvol:"
					]
				},
				{
					"name": "Trompeta d'explosió",
					"entries": [
						"Tota criatura a dins del amb ha de salvar per Constitució amb {@dc 14}. Qui falli rep 17 ({@damage 5d6}) de dany de tro i està {@condition eixordat} durant 1 minut. Qui superi en rep la meitat i no està {@condition eixordat}. Els objectes no màgics del con que no s'aguanten ni es porten prenen 35 ({@damage 10d6}) de dany de tro."
					]
				},
				{
					"name": "Trompeta d'espurnes",
					"entries": [
						"Creatures in the cone ha de salvar per Constitució amb {@dc 14}, prenant 22 ({@damage 4d8 + 4}) de dany radiant; si supera, en rep la meitat. Les criatures malvades tenen desavantatge en la tirada de salvació. Les bones criatures del con no tenen cap dany."
					]
				}
			],
			"hasToken": true,
			"traitTags": [
				"Armament Màgic"
			],
			"languageTags": [
				"CE",
				"TP"
			],
			"damageTags": [
				"P",
				"R",
				"T"
			],
			"spellcastingTags": [
				"I"
			],
			"miscTags": [
				"AOE",
				"MW"
			],
			"conditionInflict": [
				"eixordat"
			],
			"conditionInflictSpell": [
				"incapacitat"
			],
			"hasFluff": true,
			"hasFluffImages": true
		},
		{
			"name": "Cònsol de Ferro",
			"source": "BGDIA",
			"page": 232,
			"size": "M",
			"type": {
				"type": "humanoide",
				"tags": [
					"humà"
				]
			},
			"alineament": [
				"L",
				"E"
			],
			"ac": [
				{
					"ac": 16,
					"from": [
						"{@item cota de malla|phb}"
					]
				}
			],
			"hp": {
				"average": 45,
				"formula": "6d8 + 18"
			},
			"speed": {
				"walk": 30
			},
			"str": 17,
			"dex": 11,
			"con": 16,
			"int": 12,
			"wis": 15,
			"cha": 16,
			"save": {
				"wis": "+4"
			},
			"skill": {
				"intimidation": "+5",
				"perception": "+4"
			},
			"passive": 14,
			"conditionImmune": [
				"acovardit"
			],
			"idiomes": [
				"Comú"
			],
			"cr": "2",
			"trait": [
				{
					"name": "Disciplina tàctica",
					"entries": [
						"El cònsol de ferro té avantatge en totes les proves d'habilitat i en els tirs de salvació realitzats durant el combat."
					]
				}
			],
			"action": [
				{
					"name": "Multiatac",
					"entries": [
						"El cònsol de ferro fa un atac amb la seva llança i pot utilitzar la seva habilitat Veu de comandament."
					]
				},
				{
					"name": "Llança",
					"entries": [
						"{@atk mw,rw} {@hit 5} a impactar, 5 peus d'abast o 20/60 peus d'abast, un objectiu. {@h}6 ({@damage 1d6 + 3}) de dany perforant, o 7 ({@damage 1d8 + 3}) de dany perforant si s'usa amb dos mans to make a melee attack."
					]
				},
				{
					"name": "Veu de comandament",
					"entries": [
						"El cònsol de ferro selecciona fins a dos aliats a 90 peus d'ell que poden escoltar les seves ordres. Cada aliat pot utilitzar immediatament la seva reacció per fer un atac cos a cos."
					]
				}
			],
			"hasToken": true,
			"actionTags": [
				"Multiatac"
			],
			"languageTags": [
				"C"
			],
			"damageTags": [
				"P"
			],
			"miscTags": [
				"MW",
				"RW",
				"THW"
			],
			"hasFluff": true
		},
		{
			"name": "Kostchtchie",
			"isNpc": true,
			"isNamedCreature": true,
			"source": "BGDIA",
			"page": 105,
			"size": "L",
			"type": {
				"type": "infernal",
				"tags": [
					"dimoni"
				]
			},
			"alineament": [
				"C",
				"E"
			],
			"ac": [
				{
					"ac": 16,
					"from": [
						"armadura natural"
					]
				}
			],
			"hp": {
				"average": 243,
				"formula": "18d10 + 144"
			},
			"speed": {
				"walk": 40
			},
			"str": 30,
			"dex": 12,
			"con": 27,
			"int": 18,
			"wis": 22,
			"cha": 19,
			"save": {
				"dex": "+9",
				"con": "+16",
				"wis": "+14"
			},
			"skill": {
				"intimidation": "+12",
				"perception": "+14",
				"survival": "+14"
			},
			"senses": [
				"visió veraç 120 peus"
			],
			"passive": 24,
			"resist": [
				"foc",
				"elèctric"
			],
			"immune": [
				"fred",
				"verí",
				{
					"immune": [
						"contundent",
						"perforant",
						"tallant"
					],
					"note": "d'atacs no màgics",
					"cond": true
				}
			],
			"conditionImmune": [
				"fascinat",
				"acovardit",
				"emmetzinat"
			],
			"idiomes": [
				"Abismal",
				"Gegantès",
				"telepatia 120 peus"
			],
			"cr": "25",
			"spellcasting": [
				{
					"name": "Llançament de conjurs Innat",
					"headerEntries": [
						"L'habilitat de llançament de conjurs innat de Kostchtchie's és Saviesa ({@dc 20} per salvar conjur). Pot llançar els conjurs següents innatament (no necessiten components materials):"
					],
					"will": [
						"{@ordre ortogràfica}",
						"{@spell foscor}"
					],
					"daily": {
						"1e": [
							"{@spell dissipar el bé i el mal}",
							"{@spell portal}",
							"{@spell malmenar}",
							"{@spell Telequinesi}",
							"{@spell teleportació}",
							"{@spell pas del vent}"
						]
					},
					"ability": "xa"
				}
			],
			"trait": [
				{
					"name": "Resistència Llegendària (3/Dia)",
					"entries": [
						"Si Kostchtchie falla una tirada de salvació pot escollir superar-la."
					]
				},
				{
					"name": "Resistència a la Màgia",
					"entries": [
						"Kostchtchie té avantatge a salvar contra conjurs i altres efectes màgics."
					]
				}
			],
			"action": [
				{
					"name": "Multiatac",
					"entries": [
						"Kostchtchie fa dos atacs cos a cos, només un dels quals pot ser un atac de mossegada."
					]
				},
				{
					"name": "Mossegada",
					"entries": [
						"{@atk mw} {@hit 18} a impactar, 5 peus d'abast, una criatura. {@h}13 ({@damage 1d6 + 10}) de dany perforant."
					]
				},
				{
					"name": "Matalotok (Martell de guerra)",
					"entries": [
						"{@atk mw} {@hit 18} a impactar, 10 peus d'abast, un objectiu. {@h}19 ({@damage 2d8 + 10}) de dany contundent, o 21 ({@damage 2d10 + 10}) de dany contundent si s'usa amb dos mans, i l'arma emet un esclat de fred que fa 10 ({@damage 3d6}) de dany de fred a cada criatura a 30 peus d'ella."
					]
				}
			],
			"legendary": [
				{
					"name": "Atacar",
					"entries": [
						"Kostchtchie fa un atac armat cos a cos."
					]
				},
				{
					"name": "Carregar",
					"entries": [
						"Kostchtchie es mou a la seva velocitat."
					]
				},
				{
					"name": "Curse (Costa 2 Accions)",
					"entries": [
						"Kostchtchie maleeix una criatura que pot veure a 60 peus d'ell. La criatura maleïda guanya vulnerabilitat a tots els danys infligits per Kostchtchie fins al final del següent torn de Kostchtchie."
					]
				}
			],
			"hasToken": true,
			"traitTags": [
				"Resistències Llegendàries",
				"Resistència a la Màgia"
			],
			"senseTags": [
				"U"
			],
			"actionTags": [
				"Multiatac"
			],
			"languageTags": [
				"AB",
				"GI",
				"TP"
			],
			"damageTags": [
				"B",
				"C",
				"P"
			],
			"spellcastingTags": [
				"I"
			],
			"miscTags": [
				"MW",
				"RCH"
			],
			"hasFluff": true,
			"hasFluffImages": true
		},
		{
			"name": "Krull",
			"isNpc": true,
			"source": "BGDIA",
			"page": 110,
			"size": "M",
			"type": {
				"type": "humanoide",
				"tags": [
					"tòrtel"
				]
			},
			"alineament": [
				"L",
				"E"
			],
			"ac": [
				{
					"ac": 17,
					"from": [
						"armadura natural"
					]
				}
			],
			"hp": {
				"average": 117,
				"formula": "18d8 + 36"
			},
			"speed": {
				"walk": 30
			},
			"str": 20,
			"dex": 14,
			"con": 15,
			"int": 12,
			"wis": 20,
			"cha": 12,
			"save": {
				"wis": "+8",
				"cha": "+4"
			},
			"skill": {
				"arcana": "+4",
				"medicine": "+8",
				"nature": "+4",
				"survival": "+8"
			},
			"passive": 15,
			"idiomes": [
				"Aquà",
				"Comú",
				"Dracònic"
			],
			"cr": "6",
			"spellcasting": [
				{
					"name": "Llançament de Conjurs",
					"headerEntries": [
						"Krull és un llançador de conjurs de nivell 14. La seva habilitat de llançament de conjur és Saviesa ({@dc 16} salvada de conjur, {@hit 8} a impactar amb atacs màgics). Té els següents conjurs de clergue preparats:"
					],
					"spells": {
						"0": {
							"spells": [
								"{@spell mà morta}",
								"{@spell apedaçar}",
								"{@spell resistència}",
								"{@spell flama sagrada}",
								"{@spell misericòrdia}",
								"{@spell taumatúrgia}"
							]
						},
						"1": {
							"slots": 4,
							"spells": [
								"{@spell curar ferides}",
								"{@spell detecta el bé i el mal}",
								"{@spell pseudo vida}",
								"{@spell infligir ferides}",
								"{@spell raig d'arcada}"
							]
						},
						"2": {
							"slots": 3,
							"spells": [
								"{@spell ceguera/sordera}",
								"{@spell repòs gentil}",
								"{@spell immobilitzar humanoide}",
								"{@spell raig d'afebliment}",
								"{@spell arma espiritual}"
							]
						},
						"3": {
							"slots": 3,
							"spells": [
								"{@spell animar els morts}",
								"{@spell cercle màgic}",
								"{@spell parlar amb els morts}",
								"{@spell guardians espirituals}",
								"{@spell toc vampíric}"
							]
						},
						"4": {
							"slots": 3,
							"spells": [
								"{@spell desterrament}",
								"{@spell plaga}",
								"{@spell abjurar la mort}",
								"{@spell endevinació}",
								"{@spell localitzar criatura}"
							]
						},
						"5": {
							"slots": 2,
							"spells": [
								"{@spell closca contravida}",
								"{@spell matanúvol}",
								"{@spell contagiar}",
								"{@spell restabliment superior}"
							]
						},
						"6": {
							"slots": 1,
							"spells": [
								"{@spell crear no-morts}",
								"{@spell visió veritable}"
							]
						},
						"7": {
							"slots": 1,
							"spells": [
								"{@spell mot diví}",
								"{@spell regeneració}"
							]
						}
					},
					"ability": "sabia"
				}
			],
			"trait": [
				{
					"name": "Aguantar la Respiració",
					"entries": [
						"Krull pot aguantar la respiració durant 1 hora."
					]
				},
				{
					"name": "Destrucció ineludible",
					"entries": [
						"El dany necròtic causat pels encanteris de Krull ignora la resistència al dany necròtic."
					]
				}
			],
			"action": [
				{
					"name": "Urpes",
					"entries": [
						"{@atk mw} {@hit 8} a impactar, 5 peus d'abast, un objectiu. {@h}7 ({@damage 1d4 + 5}) de dany perforant."
					]
				},
				{
					"name": "Maul +1",
					"entries": [
						"{@atk mw} {@hit 9} a impactar, 5 peus d'abast, un objectiu. {@h}13 ({@damage 2d6 + 6}) de dany contundent mes 9 ({@damage 2d8}) de dany necròtic."
					]
				},
				{
					"name": "Defensa Closca",
					"entries": [
						"Krull es retira a la seva closca. Fins que no surt com a bonus d'acció, té un +4 a l'AC i té avantatge en tirs de salvació de Força i Constitució. Mentre està a la seva closca, Krull és {@condition enderrocat}, la seva velocitat és 0 i no pot augmentar, té desavantatge en els tirs de salvació de Destresa, no pot prendre reaccions i l'única acció que pot fer és sortir del seu closca."
					]
				}
			],
			"hasToken": true,
			"traitTags": [
				"Aguantar la Respiració"
			],
			"languageTags": [
				"AQ",
				"C",
				"DR"
			],
			"damageTags": [
				"B",
				"N",
				"P"
			],
			"spellcastingTags": [
				"CC"
			],
			"miscTags": [
				"MW"
			],
			"conditionInflictSpell": [
				"encegat",
				"eixordat",
				"incapacitat",
				"paralitzat",
				"emmetzinat",
				"atordit"
			],
			"hasFluffImages": true
		},
		{
			"name": "Lulu",
			"isNpc": true,
			"source": "BGDIA",
			"page": 5,
			"_copy": {
				"name": "Hollyphant",
				"source": "BGDIA",
				"_mod": {
					"*": {
						"mode": "substituirTxt",
						"replace": "el grèvol",
						"with": "Lulu",
						"flags": "i"
					}
				}
			},
			"hasToken": true
		},
		{
			"name": "Maggie boja",
			"isNpc": true,
			"source": "BGDIA",
			"page": 74,
			"_copy": {
				"name": "Bruja nocturna",
				"source": "MM",
				"_mod": {
					"*": {
						"mode": "substituirTxt",
						"replace": "la bruja",
						"with": "Maggie",
						"flags": "i"
					}
				}
			},
			"hasToken": true
		},
		{
			"name": "Mahadi el Rakshasa",
			"isNpc": true,
			"source": "BGDIA",
			"page": 127,
			"size": "M",
			"type": "infernal",
			"alineament": [
				"L",
				"E"
			],
			"ac": [
				{
					"ac": 17,
					"from": [
						"armadura natural"
					]
				}
			],
			"hp": {
				"average": 195,
				"formula": "23d8 + 92"
			},
			"speed": {
				"walk": 40
			},
			"str": 14,
			"dex": 18,
			"con": 18,
			"int": 14,
			"wis": 18,
			"cha": 20,
			"save": {
				"wis": "+9",
				"cha": "+10"
			},
			"skill": {
				"arcana": "+7",
				"deception": "+10",
				"insight": "+9",
				"perception": "+9"
			},
			"senses": [
				"visió de foscor 120 peus"
			],
			"passive": 19,
			"resist": [
				{
					"resist": [
						"contundent",
						"perforant",
						"tallant"
					],
					"note": "d'atacs no màgics",
					"cond": true
				}
			],
			"vulnerable": [
				{
					"vulnerable": [
						"perforant"
					],
					"note": "d'arma màgica emprada per bones criatures",
					"cond": true
				}
			],
			"idiomes": [
				"tot (només es pot llegir)",
				"Comú",
				"Diàstric"
			],
			"cr": "14",
			"spellcasting": [
				{
					"name": "Llançament de conjurs Innat",
					"headerEntries": [
						"L'habilitat de llançament de conjurs innata de Mahadi és Carisma ({@dc 18} salvada de conjur, {@hit 9} a impactar amb atacs màgics). Pot llançar els conjurs següents innatament (no necessiten components materials):"
					],
					"will": [
						"{@spell detectar pensaments}",
						"{@spell ego camuflatge}",
						"{@spell mà de mag}",
						"{@spell il·lusió menor}"
					],
					"daily": {
						"3e": [
							"{@spell fascinar persona}",
							"{@spell detectar màgia}",
							"{@spell dissipar màgia}",
							"{@spell venjança dels inferns}",
							"{@spell invisibilitat}",
							"{@spell imatge major}",
							"{@spell parlar amb els morts}",
							"{@spell suggestió}"
						],
						"1e": [
							"{@spell desterrament}",
							"{@spell demiplà}",
							"{@spell dominar humanoide}",
							"{@spell volar}",
							"{@spell gàbia de força}",
							"{@spell geas}",
							"{@spell saltar de pla}",
							"{@spell visió veritable}"
						]
					},
					"ability": "xa"
				}
			],
			"trait": [
				{
					"name": "Immunitat Màgica Limitada",
					"entries": [
						"Mahadi no pot ser afectat ni detectat per encanteris de 6è nivell o inferior tret que ho desitgi. Té avantatges a salvades contra conjurs i altres efectes màgics."
					]
				},
				{
					"name": "Armament Màgic",
					"entries": [
						"Els atacs armats de Mahadi's són màgics."
					]
				}
			],
			"action": [
				{
					"name": "Multiatac",
					"entries": [
						"Mahadi fa quatre atacs d'Urpa."
					]
				},
				{
					"name": "Urpa",
					"entries": [
						"{@atk mw} {@hit 7} a impactar, 5 peus d'abast, un objectiu. {@h}9 ({@damage 2d6 + 2}) de dany tallant, i l'objectiu està maleït si és una criatura. La maledicció té efecte sempre que l'objectiu pren un descans curt o llarg, omplint els seus pensaments d'imatges i somnis horribles. L'objectiu maleït no treu cap benefici en acabar un descans curt o llarg. La maledicció dura fins que és aixecada per un encanteri anul·lar maledicció o màgia semblant."
					]
				},
				{
					"name": "Convocar Erinyes (1/dia)",
					"entries": [
						"Mahadi convoca Ilzabet, una erinyes lligada a ell per un contracte infernal. Les erinyes apareixen en un espai desocupat a 60 peus d'ell, actua com a seu aliat i no poden convocar altres diables. Les erinyes romanen durant 10 minuts o fins que Mahadi la desestima com a acció. Si l'erinyes mor, Mahadi perd aquesta opció d'acció."
					]
				}
			],
			"hasToken": true,
			"traitTags": [
				"Armament Màgic"
			],
			"senseTags": [
				"SD"
			],
			"actionTags": [
				"Multiatac"
			],
			"languageTags": [
				"C",
				"I",
				"XX"
			],
			"damageTags": [
				"S"
			],
			"spellcastingTags": [
				"I"
			],
			"miscTags": [
				"MW"
			],
			"hasFluff": true,
			"hasFluffImages": true
		},
		{
			"name": "Mestre de les ànimes",
			"source": "BGDIA",
			"page": 234,
			"size": "M",
			"type": {
				"type": "humanoide",
				"tags": [
					"humà"
				]
			},
			"alineament": [
				"N",
				"E"
			],
			"ac": [
				12
			],
			"hp": {
				"average": 45,
				"formula": "6d8 + 18"
			},
			"speed": {
				"walk": 30
			},
			"str": 10,
			"dex": 14,
			"con": 17,
			"int": 19,
			"wis": 14,
			"cha": 13,
			"save": {
				"wis": "+4"
			},
			"skill": {
				"arcana": "+6",
				"religion": "+6"
			},
			"passive": 12,
			"idiomes": [
				"Abismal",
				"Comú",
				"Diàstric"
			],
			"cr": "4",
			"spellcasting": [
				{
					"name": "Llançament de Conjurs",
					"headerEntries": [
						"The master of souls és llançador/a de conjurs de nivell 5. La seva habilitat de llançament de conjurs és Intel·ligència ({@dc 14} salvada de conjur, {@hit 6} a impactar amb atacs màgics). Té els següents conjurs de mag preparats:"
					],
					"spells": {
						"0": {
							"spells": [
								"{@spell mà morta} (vegeu \"Accions\" a continuació)",
								"{@spell mà de mag}",
								"{@spell missatge}",
								"{@spell prestidigitació}"
							]
						},
						"1": {
							"slots": 4,
							"spells": [
								"{@spell mans ardents}",
								"{@spell detectar màgia}",
								"{@spell raig d'arcada} (vegeu \"Accions\" a continuació)",
								"{@spell escut}"
							]
						},
						"2": {
							"slots": 3,
							"spells": [
								"{@spell foscor}",
								"{@spell pas boira}",
								"{@spell raig d'incendi} (vegeu \"Accions\" a continuació)"
							]
						},
						"3": {
							"slots": 2,
							"spells": [
								"{@spell animar els morts}",
								"{@spell bola de foc}"
							]
						}
					},
					"ability": "int"
				}
			],
			"trait": [
				{
					"name": "Màgia Grave",
					"entries": [
						"Quan el mestre de les ànimes llança un encanteri que fa dany, pot canviar el tipus de dany de l'encanteri a necròtic."
					]
				}
			],
			"action": [
				{
					"name": "Multiatac",
					"entries": [
						"El mestre de les ànimes ataca dues vegades amb el seu flagell."
					]
				},
				{
					"name": "Calavera plateada",
					"entries": [
						"{@atk mw} {@hit 2} a impactar, 5 peus d'abast, un objectiu. {@h}4 ({@damage 1d8}) de dany contundent mes 14 ({@damage 4d6}) de dany necròtic, i l'objectiu té desavantatge en totes les tirades de salvació fins al final del següent torn del mestre de les ànimes."
					]
				},
				{
					"name": "Mà Morta (Truc)",
					"entries": [
						"{@atk rs} {@hit 6} a impactar, 120 peus d'abast, una criatura. {@h}13 ({@damage 2d8}) de dany necròtic, i l'objectiu no pot recuperar punts de vida fins que comenci el proper torn del mestre de les ànimes. Si l'objectiu és no mort, té un desavantatge a les tires d'atac contra el mestre de les ànimes durant la mateixa durada."
					]
				},
				{
					"name": "Raig d'Arcada (Encanteri de 1r nivell; Requereix un espai per a encanteris)",
					"entries": [
						"{@atk rs} {@hit 6} a impactar, 60 peus d'abast, una criatura. {@h}9 ({@damage 2d8}) de dany de verí, i l'objectiu ha de superar una salvada de Constitució amb {@dc 14} o be {@condition emmetzinat} fins al final del mestre de les ànimes' torn següent. Si el mestre de les ànimes llança aquest encanteri utilitzant un espai d'encanteri de 2n nivell o superior, el dany incrementa en {@dice 1d8} per cada nivell per sobre d'1."
					]
				},
				{
					"name": "Raig d'Incendi (Encanteri de 2n nivell; Requereix un espai per a encanteris)",
					"entries": [
						"{@atk rs} {@hit 6} a impactar, 120 peus d'abast, un objectiu per ray (3 raigs si s'utilitza una ranura d'encanteris de 2n nivell, 4 rajos si s'utilitza una ranura d'encanteris de 3r nivell). {@h}7 ({@damage 2d6}) de dany de foc per ray."
					]
				}
			],
			"hasToken": true,
			"actionTags": [
				"Multiatac"
			],
			"languageTags": [
				"AB",
				"C",
				"I"
			],
			"damageTags": [
				"B",
				"F",
				"I",
				"N"
			],
			"spellcastingTags": [
				"CW"
			],
			"miscTags": [
				"MW"
			],
			"conditionInflict": [
				"emmetzinat"
			],
			"conditionInflictSpell": [
				"emmetzinat"
			],
			"hasFluff": true
		},
		{
			"name": "Mortlock Vanthampur",
			"isNpc": true,
			"source": "BGDIA",
			"page": 26,
			"size": "M",
			"type": {
				"type": "humanoide",
				"tags": [
					"humà"
				]
			},
			"alineament": [
				"L",
				"E"
			],
			"ac": [
				12
			],
			"hp": {
				"average": 90,
				"formula": "12d8 + 36"
			},
			"speed": {
				"walk": 30
			},
			"str": 18,
			"dex": 14,
			"con": 17,
			"int": 10,
			"wis": 12,
			"cha": 13,
			"skill": {
				"athletics": "+6",
				"intimidation": "+5"
			},
			"passive": 11,
			"idiomes": [
				"Comú"
			],
			"cr": "3",
			"trait": [
				{
					"name": "Indomable (2/dia)",
					"entries": [
						"Mortlock pot tornar a tirar una tirada de salvació que falla. Ha d'utilitzar la nova tirada."
					]
				}
			],
			"action": [
				{
					"name": "Multiatac",
					"entries": [
						"Mortlock fa dos atacs amb el seu gran club."
					]
				},
				{
					"name": "Gran club",
					"entries": [
						"{@atk mw} {@hit 6} a impactar, 5 peus d'abast, un objectiu. {@h}9 ({@damage 2d4 + 4}) de dany contundent, mes 5 ({@damage 2d4}) de dany contundent si Mortlock ha patit algun dany des del seu darrer torn."
					]
				},
				{
					"name": "Ballesta Pesada",
					"entries": [
						"{@atk rw} {@hit 4} a impactar, 100/400 peus d'abast, un objectiu. {@h}7 ({@damage 1d10 + 2}) de dany perforant."
					]
				}
			],
			"hasToken": true,
			"actionTags": [
				"Multiatac"
			],
			"languageTags": [
				"C"
			],
			"damageTags": [
				"B",
				"P"
			],
			"miscTags": [
				"MW",
				"RNG",
				"RW"
			],
			"hasFluff": true,
			"hasFluffImages": true
		},
		{
			"name": "Necròmita de Myrkul",
			"source": "BGDIA",
			"page": 234,
			"size": "M",
			"type": {
				"type": "humanoide",
				"tags": [
					"humà"
				]
			},
			"alineament": [
				"N",
				"E"
			],
			"ac": [
				11
			],
			"hp": {
				"average": 13,
				"formula": "2d8 + 4"
			},
			"speed": {
				"walk": 30
			},
			"str": 10,
			"dex": 13,
			"con": 15,
			"int": 16,
			"wis": 11,
			"cha": 10,
			"skill": {
				"arcana": "+5",
				"religion": "+5"
			},
			"passive": 10,
			"idiomes": [
				"Abismal",
				"Comú",
				"Diàstric"
			],
			"cr": "1/2",
			"action": [
				{
					"name": "Calavera de calavera",
					"entries": [
						"{@atk mw} {@hit 2} a impactar, 5 peus d'abast, un objectiu. {@h}4 ({@damage 1d8}) de dany contundent."
					]
				},
				{
					"name": "Les urpes de la tomba",
					"entries": [
						"{@atk rs} {@hit 5} a impactar, 90 peus d'abast, un objectiu. {@h}8 ({@damage 2d4 + 3}) de dany necròtic."
					]
				}
			],
			"hasToken": true,
			"languageTags": [
				"AB",
				"C",
				"I"
			],
			"damageTags": [
				"B",
				"N"
			],
			"miscTags": [
				"MW"
			],
			"hasFluff": true,
			"hasFluffImages": true
		},
		{
			"name": "Centpeus necròtic",
			"source": "BGDIA",
			"page": 119,
			"_copy": {
				"name": "Remorhaz",
				"source": "MM",
				"_mod": {
					"*": {
						"mode": "substituirTxt",
						"replace": "remorhaz",
						"with": "centpeus"
					},
					"action": {
						"mode": "substituirArr",
						"replace": "Mossegada",
						"items": {
							"name": "Mossegada",
							"entries": [
								"{@atk mw} {@hit 11} a impactar, 10 peus d'abast, un objectiu. {@h}40 ({@damage 6d10 + 7}) de dany perforant mes 10 ({@damage 3d6}) de dany necròtic. Si l'objectiu és una criatura, és {@condition grappled} ({@dc 17} per escapar). Fins que s'acabi aquesta presa, l'objectiu està {@condition restrained}, i el centpeus no pot mossegar un altre objectiu."
							]
						}
					}
				}
			},
			"immune": [
				"necròtic",
				"foc"
			],
			"trait": [
				{
					"name": "Cos necròtic",
					"entries": [
						"Una criatura que toca el centpeus o el colpeja amb un atac cos a cos a menys de 5 peus d'aquest triga 10 ({@damage 3d6}) de dany necròtic."
					]
				}
			],
			"hasToken": true,
			"damageTags": [
				"A",
				"N",
				"P"
			]
		},
		{
			"name": "Night Blade",
			"source": "BGDIA",
			"page": 233,
			"size": "M",
			"type": {
				"type": "humanoide",
				"tags": [
					"humà"
				]
			},
			"alineament": [
				"C",
				"E"
			],
			"ac": [
				12
			],
			"hp": {
				"average": 11,
				"formula": "2d8 + 2"
			},
			"speed": {
				"walk": 40
			},
			"str": 11,
			"dex": 15,
			"con": 12,
			"int": 10,
			"wis": 11,
			"cha": 14,
			"skill": {
				"intimidation": "+4",
				"stealth": "+6"
			},
			"senses": [
				"visió fosca 60"
			],
			"passive": 10,
			"idiomes": [
				"Comú"
			],
			"cr": "1/4",
			"trait": [
				{
					"name": "Aura d'assassinat",
					"entries": [
						"Mentre la fulla nocturna no sigui {@condition incapacitat}, les criatures hostils a menys de 5 peus d'ella guanyen vulnerabilitat a danys perforants tret que tinguin resistència o immunitat a aquests danys."
					]
				}
			],
			"action": [
				{
					"name": "Daga",
					"entries": [
						"{@atk mw,rw} {@hit 4} a impactar, 5 peus d'abast o 20/60 peus d'abast, un objectiu. {@h}4 ({@damage 1d4 + 2}) de dany perforant."
					]
				}
			],
			"hasToken": true,
			"senseTags": [
				"D"
			],
			"languageTags": [
				"C"
			],
			"damageTags": [
				"P"
			],
			"miscTags": [
				"MW",
				"RW",
				"THW"
			],
			"hasFluff": true
		},
		{
			"name": "Keene de nou dits",
			"isNpc": true,
			"source": "BGDIA",
			"page": 170,
			"size": "M",
			"type": {
				"type": "humanoide",
				"tags": [
					"humà"
				]
			},
			"alineament": [
				"N"
			],
			"ac": [
				{
					"ac": 15,
					"from": [
						"{@item armadura de cuir|phb}"
					]
				}
			],
			"hp": {
				"average": 84,
				"formula": "13d8 + 26"
			},
			"speed": {
				"walk": 30
			},
			"str": 12,
			"dex": 18,
			"con": 14,
			"int": 13,
			"wis": 17,
			"cha": 14,
			"save": {
				"dex": "+7",
				"int": "+4"
			},
			"skill": {
				"acrobatics": "+10",
				"deception": "+5",
				"insight": "+6",
				"intimidation": "+5",
				"perception": "+6",
				"sleight of hand": "+10",
				"stealth": "+10"
			},
			"passive": 16,
			"idiomes": [
				"Comú",
				"Argot de Lladres"
			],
			"cr": "5",
			"trait": [
				{
					"name": "Acció Astuta",
					"entries": [
						"En cadascun dels seus torns en combat, Nine-Fingers pot Córrer, Destravar-se o Amagar-se com a acció bonus."
					]
				},
				{
					"name": "Llançador de punyals",
					"entries": [
						"Nine-Fingers afegeix el doble de la seva bonificació de competència al dany que fa als atacs a distància realitzats amb punyals (ja es tenen en compte en els seus atacs)."
					]
				}
			],
			"action": [
				{
					"name": "Multiatac",
					"entries": [
						"Nine-Fingers ataca tres vegades amb les seves dagues."
					]
				},
				{
					"name": "Daga",
					"entries": [
						"{@atk mw,rw} {@hit 7} a impactar, 5 peus d'abast o 20/60 peus d'abast, un objectiu. {@h}6 ({@damage 1d4 + 4}) de dany perforant, mes 6 de dany perforant si és un atac a distància."
					]
				}
			],
			"reaction": [
				{
					"name": "Esquivar l'Impossible",
					"entries": [
						"Nine-Fingers redueix a la meitat el dany que rep d'un atac que la colpeja. Ha de ser capaç de veure l'atacant."
					]
				}
			],
			"hasToken": true,
			"actionTags": [
				"Multiatac"
			],
			"languageTags": [
				"C",
				"TC"
			],
			"damageTags": [
				"P"
			],
			"miscTags": [
				"MW",
				"RW",
				"THW"
			],
			"hasFluff": true,
			"hasFluffImages": true
		},
		{
			"name": "Paó",
			"source": "BGDIA",
			"page": 195,
			"_copy": {
				"name": "Voltor",
				"source": "MM",
				"_mod": {
					"*": {
						"mode": "substituirTxt",
						"replace": "voltor",
						"with": "paó"
					}
				}
			},
			"hasToken": true
		},
		{
			"name": "Princeps Kovik",
			"isNpc": true,
			"source": "BGDIA",
			"page": 91,
			"_copy": {
				"name": "Diable de cadena",
				"source": "MM",
				"_mod": {
					"*": {
						"mode": "substituirTxt",
						"replace": "el diable",
						"with": "Kovik",
						"flags": "i"
					}
				}
			},
			"hasToken": true
		},
		{
			"name": "Raggadragga",
			"isNpc": true,
			"source": "BGDIA",
			"page": 87,
			"_copy": {
				"name": "Senglar home",
				"source": "MM",
				"_mod": {
					"*": {
						"mode": "substituirTxt",
						"replace": "el senglar",
						"with": "Raggadragga",
						"flags": "i"
					}
				}
			},
			"hp": {
				"average": 120,
				"formula": "12d8 + 24"
			},
			"hasToken": true
		},
		{
			"name": "Segador de Bhaal",
			"source": "BGDIA",
			"page": 233,
			"size": "M",
			"type": {
				"type": "humanoide",
				"tags": [
					"humà"
				]
			},
			"alineament": [
				"C",
				"E"
			],
			"ac": [
				15
			],
			"hp": {
				"average": 27,
				"formula": "5d8 + 5"
			},
			"speed": {
				"walk": 40
			},
			"str": 11,
			"dex": 20,
			"con": 13,
			"int": 15,
			"wis": 12,
			"cha": 16,
			"skill": {
				"intimidation": "+5",
				"perception": "+3",
				"persuasion": "+5",
				"stealth": "+9"
			},
			"senses": [
				"visió de foscor 60 peus"
			],
			"passive": 13,
			"idiomes": [
				"Comú"
			],
			"cr": "2",
			"spellcasting": [
				{
					"name": "Llançament de conjurs Innat",
					"headerEntries": [
						"L'habilitat de llançament de conjurs innat de The reaper's és Saviesa ({@dc 13} per salvar conjur). Pot llançar els conjurs següents innatament (no necessiten components materials):"
					],
					"daily": {
						"1e": [
							"{@spell fascinar persona}",
							"{@spell ego camuflatge}",
							"{@spell santuari}"
						]
					},
					"ability": "xa"
				}
			],
			"trait": [
				{
					"name": "Aura d'assassinat",
					"entries": [
						"Mentre el segador no sigui {@condition incapacitat}, les criatures hostils a menys de 5 peus d'ell guanyen vulnerabilitat a danys perforants tret que tinguin resistència o immunitat a aquests danys."
					]
				}
			],
			"action": [
				{
					"name": "Multiatac",
					"entries": [
						"El segador fa dos atacs de punyal i utilitza Shroud Self."
					]
				},
				{
					"name": "Daga",
					"entries": [
						"{@atk mw,rw} {@hit 7} a impactar, 5 peus d'abast o 20/60 peus d'abast, un objectiu. {@h}7 ({@damage 1d4 + 5}) de dany perforant."
					]
				},
				{
					"name": "Jo sudari",
					"entries": [
						"The reaper magically turns {@condition invisible} fins a l'inici del seu següent trencat. Aquesta invisibilitat acaba si el segador fa una tirada d'atac, fa una tirada de dany o fa un encanteri."
					]
				}
			],
			"hasToken": true,
			"senseTags": [
				"D"
			],
			"actionTags": [
				"Multiatac"
			],
			"languageTags": [
				"C"
			],
			"damageTags": [
				"P"
			],
			"spellcastingTags": [
				"I"
			],
			"miscTags": [
				"MW",
				"RW",
				"THW"
			],
			"conditionInflictSpell": [
				"fascinat"
			],
			"hasFluff": true,
			"hasFluffImages": true
		},
		{
			"name": "Rilsa Rael",
			"isNpc": true,
			"source": "BGDIA",
			"page": 199,
			"size": "M",
			"type": {
				"type": "humanoide",
				"tags": [
					"humà"
				]
			},
			"alineament": [
				"N"
			],
			"ac": [
				{
					"ac": 15,
					"from": [
						"{@item armadura de cuir|phb}"
					]
				}
			],
			"hp": {
				"average": 52,
				"formula": "8d8 + 16"
			},
			"speed": {
				"walk": 30
			},
			"str": 14,
			"dex": 18,
			"con": 14,
			"int": 10,
			"wis": 11,
			"cha": 15,
			"save": {
				"dex": "+6",
				"wis": "+2"
			},
			"skill": {
				"acrobatics": "+6",
				"athletics": "+4",
				"deception": "+4",
				"perception": "+2",
				"sleight of hand": "+6",
				"stealth": "+6"
			},
			"passive": 12,
			"idiomes": [
				"Comú",
				"Argot de Lladres"
			],
			"cr": "3",
			"trait": [
				{
					"name": "Acció Astuta",
					"entries": [
						"En cadascun dels seus torns en combat, Rilsa pot Córrer, Destravar-se o Amagar-se com a bonus d'acció."
					]
				},
				{
					"name": "Focus",
					"entries": [
						"Si la Rilsa fa mal a una criatura amb un atac d'arma, obté avantatge a les tires d'atac contra aquest objectiu fins al final del seu següent torn."
					]
				},
				{
					"name": "Lideratge tàctic",
					"entries": [
						"Com a bonus d'acció, la Rilsa tria una criatura que pugui veure a menys de 30 peus d'ella. La criatura no provoca atacs d'oportunitat fins el final del seu propi trencament. sempre que pugui escoltar les ordres de la Rilsa."
					]
				}
			],
			"action": [
				{
					"name": "Multiatac",
					"entries": [
						"Rilsa fa tres atacs d'armes."
					]
				},
				{
					"name": "Espasa curta",
					"entries": [
						"{@atk mw} {@hit 6} a impactar, 5 peus d'abast, un objectiu. {@h}7 ({@damage 1d6 + 4}) de dany perforant."
					]
				},
				{
					"name": "Daga",
					"entries": [
						"{@atk mw,rw} {@hit 6} a impactar, 5 peus d'abast o 20/60 peus d'abast, un objectiu. {@h}6 ({@damage 1d4 + 4}) de dany perforant."
					]
				}
			],
			"hasToken": true,
			"actionTags": [
				"Multiatac"
			],
			"languageTags": [
				"C",
				"TC"
			],
			"damageTags": [
				"P"
			],
			"miscTags": [
				"MW",
				"RW",
				"THW"
			],
			"hasFluff": true,
			"hasFluffImages": true
		},
		{
			"name": "Rates esquelètiques",
			"source": "BGDIA",
			"page": 23,
			"_copy": {
				"name": "Eixam de rates",
				"source": "MM"
			},
			"type": {
				"type": "no mort",
				"swarmSize": "T"
			},
			"hasToken": true
		},
		{
			"name": "Llaçador de cranis de Myrkul",
			"source": "BGDIA",
			"page": 234,
			"size": "M",
			"type": {
				"type": "humanoide",
				"tags": [
					"humà"
				]
			},
			"alineament": [
				"N",
				"E"
			],
			"ac": [
				12
			],
			"hp": {
				"average": 32,
				"formula": "5d8 + 10"
			},
			"speed": {
				"walk": 30
			},
			"str": 10,
			"dex": 14,
			"con": 15,
			"int": 16,
			"wis": 13,
			"cha": 10,
			"save": {
				"wis": "+3"
			},
			"skill": {
				"arcana": "+5",
				"religion": "+5"
			},
			"passive": 11,
			"idiomes": [
				"Abismal",
				"Comú",
				"Diàstric"
			],
			"cr": "1",
			"spellcasting": [
				{
					"name": "Llançament de Conjurs",
					"headerEntries": [
						"The skull lasher és llançador/a de conjurs de nivell 3. La seva habilitat de llançament de conjurs és Saviesa (CD per salvar conjur {@dc 13}, {@hit 5} a impactar amb atacs màgics). Té els següents conjurs de mag preparats:"
					],
					"spells": {
						"0": {
							"spells": [
								"{@spell mà de mag}",
								"{@spell missatge}",
								"{@spell prestidigitació}"
							]
						},
						"1": {
							"slots": 4,
							"spells": [
								"{@spell detectar màgia}",
								"{@spell protegir del bé i del mal}",
								"{@spell raig d'arcada} (vegeu \"Accions\" a continuació)",
								"{@spell escut}"
							]
						},
						"2": {
							"slots": 2,
							"spells": [
								"{@spell foscor}",
								"{@spell pas boira}"
							]
						}
					},
					"ability": "sabia"
				}
			],
			"action": [
				{
					"name": "Multiatac",
					"entries": [
						"The skull flags fa dos atacs with its flil."
					]
				},
				{
					"name": "Calavera de ferro",
					"entries": [
						"{@atk mw} {@hit 2} a impactar, 5 peus d'abast, un objectiu. {@h}4 ({@damage 1d8}) de dany contundent mes 7 ({@damage 2d6}) de dany necròtic, i l'objectiu té desavantatge en tots els tirs de salvació fins al final del següent torn del skull flag."
					]
				},
				{
					"name": "Raig d'Arcada (Encanteri de 1r nivell; Requereix un espai per a encanteris)",
					"entries": [
						"{@atk rs} {@hit 5} a impactar, 60 peus d'abast, una criatura. {@h}9 ({@damage 2d8}) de dany de verí, i l'objectiu ha de superar una salvada de Constitució amb {@dc 13} o be {@condition emmetzinat} fins al final del torn següent del skull lasher . Si el skull flagrant llança aquest encanteri utilitzant una ranura d'encanteri de 2n nivell o superior, el dany incrementa en {@dice 1d8} per cada nivell per sobre d'1."
					]
				}
			],
			"hasToken": true,
			"actionTags": [
				"Multiatac"
			],
			"languageTags": [
				"AB",
				"C",
				"I"
			],
			"damageTags": [
				"B",
				"I",
				"N"
			],
			"spellcastingTags": [
				"CW"
			],
			"miscTags": [
				"MW"
			],
			"conditionInflict": [
				"emmetzinat"
			],
			"conditionInflictSpell": [
				"emmetzinat"
			],
			"hasFluff": true
		},
		{
			"name": "Somriu el Profanador",
			"isNpc": true,
			"source": "BGDIA",
			"page": 133,
			"size": "M",
			"type": {
				"type": "fata",
				"tags": [
					"elf"
				]
			},
			"alineament": [
				"C",
				"E"
			],
			"ac": [
				{
					"ac": 18,
					"from": [
						"{@item +2 armadura de cuir}"
					]
				}
			],
			"hp": {
				"average": 165,
				"formula": "22d8 + 66"
			},
			"speed": {
				"walk": 30
			},
			"str": 14,
			"dex": 20,
			"con": 16,
			"int": 18,
			"wis": 11,
			"cha": 18,
			"skill": {
				"deception": "+7",
				"persuasion": "+7"
			},
			"senses": [
				"visió de foscor 60 peus"
			],
			"passive": 10,
			"resist": [
				{
					"resist": [
						"contundent",
						"perforant",
						"tallant"
					],
					"note": "d'atacs no màgics",
					"cond": true
				}
			],
			"idiomes": [
				"Comú",
				"Èlfic",
				"Silvanic"
			],
			"cr": "7",
			"spellcasting": [
				{
					"name": "Llançament de conjurs Innat",
					"headerEntries": [
						"L'habilitat de llançament de conjurs innat de Smiler's és Saviesa ({@dc 15} per salvar conjur). Pot llançar els conjurs següents innatament (no necessiten components materials):"
					],
					"will": [
						"{@spell fascinar persona}",
						"{@spell Riure Horrible de la Tasha}"
					],
					"daily": {
						"3e": [
							"{@spell confusió}",
							"{@spell captivar}",
							"{@spell suggestió}"
						],
						"1e": [
							"{@spell terreny il·lusori}",
							"{@spell Dansa Irresistible de l'Otto}"
						]
					},
					"ability": "xa"
				}
			],
			"trait": [
				{
					"name": "Pas de Fata {@recharge 4}",
					"entries": [
						"Com a bonus d'acció, Smiler pot teletransportar-se un 30 peus a un espai desocupat que pot veure o al seient buit de la seva màquina de guerra infernal."
					]
				},
				{
					"name": "Resistència a la Màgia",
					"entries": [
						"Smiler té avantatge a salvar contra conjurs i altres efectes màgics."
					]
				},
				{
					"name": "Equipament",
					"entries": [
						"Smiler porta una armadura de cuir +2. Porta set monedes d'ànima en una bossa i una espasa curta +1"
					]
				}
			],
			"action": [
				{
					"name": "Multiatac",
					"entries": [
						"Smiler fa dos atacs d'armes. Pot llançar un encanteri en lloc d'un d'aquests atacs."
					]
				},
				{
					"name": "Espasa curta +1",
					"entries": [
						"{@atk mw} {@hit 9} a impactar, 5 peus d'abast, un objectiu. {@h}9 ({@damage 1d6 + 6}) de dany perforant."
					]
				}
			],
			"hasToken": true,
			"traitTags": [
				"Resistència a la Màgia"
			],
			"senseTags": [
				"D"
			],
			"actionTags": [
				"Multiatac"
			],
			"languageTags": [
				"C",
				"E",
				"S"
			],
			"damageTags": [
				"P"
			],
			"spellcastingTags": [
				"I"
			],
			"miscTags": [
				"MW"
			],
			"hasFluff": true,
			"hasFluffImages": true
		},
		{
			"name": "Sylvira Savikas",
			"isNpc": true,
			"source": "BGDIA",
			"page": 46,
			"_copy": {
				"name": "Archimat",
				"source": "MM",
				"_trait": {
					"name": "Tíflin",
					"source": "PHB"
				},
				"_mod": {
					"*": {
						"mode": "substituirTxt",
						"replace": "l'arximag",
						"with": "Sylvira",
						"flags": "i"
					},
					"_": [
						{
							"mode": "addSkills",
							"skills": {
								"investigation": 2
							}
						}
					]
				}
			},
			"alineament": [
				"L",
				"N"
			],
			"idiomes": [
				"Abismal",
				"Celestial",
				"Comú",
				"Dracònic",
				"Diàstric",
				"Primordial"
			],
			"hasToken": true,
			"languageTags": [
				"AB",
				"C",
				"CE",
				"DR",
				"I",
				"P"
			],
			"spellcastingTags": [
				"CW",
				"I"
			]
		},
		{
			"name": "Thavius ​​Kreeg",
			"isNpc": true,
			"source": "BGDIA",
			"page": 42,
			"size": "M",
			"type": {
				"type": "humanoide",
				"tags": [
					"humà"
				]
			},
			"alineament": [
				"L",
				"E"
			],
			"ac": [
				10
			],
			"hp": {
				"average": 40,
				"formula": "9d8"
			},
			"speed": {
				"walk": 30
			},
			"str": 12,
			"dex": 10,
			"con": 11,
			"int": 15,
			"wis": 18,
			"cha": 16,
			"skill": {
				"deception": "+5",
				"medicine": "+6",
				"persuasion": "+5",
				"religion": "+4"
			},
			"passive": 14,
			"idiomes": [
				"Abismal",
				"Comú",
				"Diàstric"
			],
			"cr": "1/2",
			"trait": [
				{
					"name": "L'ombra de la culpa",
					"entries": [
						"L'ombra d'en Thavius ​​és la d'un diable gordit i cornut amb ales petites."
					]
				}
			],
			"action": [
				{
					"name": "Maça",
					"entries": [
						"{@atk mw} {@hit 3} a impactar, 5 peus d'abast, un objectiu. {@h}4 ({@damage 1d6 + 1}) de dany contundent."
					]
				}
			],
			"hasToken": true,
			"languageTags": [
				"AB",
				"C",
				"I"
			],
			"damageTags": [
				"B"
			],
			"miscTags": [
				"MW"
			]
		},
		{
			"name": "Thurstwell Vanthampur",
			"isNpc": true,
			"source": "BGDIA",
			"page": 34,
			"size": "M",
			"type": {
				"type": "humanoide",
				"tags": [
					"humà"
				]
			},
			"alineament": [
				"L",
				"E"
			],
			"ac": [
				9
			],
			"hp": {
				"average": 5,
				"formula": "2d8 - 4"
			},
			"speed": {
				"walk": 30
			},
			"str": 7,
			"dex": 8,
			"con": 6,
			"int": 15,
			"wis": 17,
			"cha": 12,
			"skill": {
				"deception": "+3",
				"insight": "+5",
				"perception": "+5",
				"religion": "+4"
			},
			"passive": 15,
			"idiomes": [
				"Comú",
				"Èlfic",
				"Diàstric"
			],
			"cr": "1/8",
			"spellcasting": [
				{
					"name": "Llançament de Conjurs",
					"headerEntries": [
						"Thurstwell és llançador/a de conjurs de nivell 2. La seva habilitat de llançament de conjurs és Saviesa ({@dc 13} salvació de conjur). Té els següents conjurs de clergue preparats:"
					],
					"spells": {
						"0": {
							"spells": [
								"{@spell guia}",
								"{@spell flama sagrada} (vegeu \"Accions\" a continuació)",
								"{@spell taumatúrgia}"
							]
						},
						"1": {
							"slots": 3,
							"spells": [
								"{@ordre ortogràfica}",
								"{@spell detecta el bé i el mal}",
								"{@spell santuari}"
							]
						}
					},
					"ability": "sabia"
				}
			],
			"trait": [
				{
					"name": "Devoció fosca",
					"entries": [
						"Thurstwell té avantatge a salvar contra ser {@condition fascinat} o {@condition acovardit}."
					]
				}
			],
			"action": [
				{
					"name": "Flama Sagrada (Truc)",
					"entries": [
						"Un resplendor semblant a una flama descendeix sobre una criatura que Thurstwell pot veure a 60 peus d'ell. L'objectiu ha de salvar per Destresa amb {@dc 13} o prendre 4 ({@damage 1d8}) de dany radiant, sense obtenir cap benefici de la cobertura."
					]
				}
			],
			"hasToken": true,
			"languageTags": [
				"C",
				"E",
				"I"
			],
			"damageTags": [
				"R"
			],
			"spellcastingTags": [
				"CC"
			],
			"conditionInflictSpell": [
				"enderrocat"
			],
			"hasFluff": true,
			"hasFluffImages": true
		},
		{
			"name": "Torogar Puny d'acer",
			"isNpc": true,
			"source": "BGDIA",
			"page": 112,
			"size": "L",
			"type": "monstrositat",
			"alineament": [
				"L",
				"E"
			],
			"ac": [
				{
					"ac": 17,
					"from": [
						"armadura natural"
					]
				}
			],
			"hp": {
				"average": 168,
				"formula": "16d10 + 80"
			},
			"speed": {
				"walk": 40
			},
			"str": 25,
			"dex": 17,
			"con": 20,
			"int": 8,
			"wis": 9,
			"cha": 16,
			"save": {
				"str": "+11",
				"con": "+9"
			},
			"senses": [
				"visió de foscor 60 peus"
			],
			"passive": 9,
			"idiomes": [
				"Abismal",
				"Comú"
			],
			"cr": "11",
			"trait": [
				{
					"name": "Càrrega Empaladora",
					"entries": [
						"Immediatament després d'utilitzar l'acció Dash, Torogar pot fer un atac cos a cos amb les seves banyes."
					]
				},
				{
					"name": "Enteniment Laberíntic",
					"entries": [
						"Torogar recorda perfectament qualsevol camí que hagi recorregut."
					]
				},
				{
					"name": "Rage (es Recarrega amb un descans Curt o Llarg)",
					"entries": [
						"Com a bonus d'acció, Torogar pot entrar en una ràbia que dura 1 minut. La ràbia s'acaba aviat si el Torogar és colpejat {@condition inconscient} o si el seu torn acaba i no ha atacat cap criatura hostil ni ha patit dany des del seu darrer torn. Mentre s'enfada, Torogar obté els següents beneficis:",
						"Té avantatge a les jugades del Força i als tirs de salvació del Força.",
						"Inflige 3 danys addicionals quan colpeja un objectiu amb un atac armat com a cos.",
						"Té resistència a dany contundent, tallant, i perforant."
					]
				},
				{
					"name": "Equipament Especial",
					"entries": [
						"Torogar porta {@item guants de fúria flamígera|bgdia} i un {@item cinturó de foc gegant de força}. Sense el cinturó, la seva Força és de 21. També porta una {@item soul coin|bgdia}."
					]
				}
			],
			"action": [
				{
					"name": "Multiatac",
					"entries": [
						"Torogar fa tres atacs: dos amb la cimitarra i un amb les banyes."
					]
				},
				{
					"name": "Simitarra",
					"entries": [
						"{@atk mw} {@hit 11} a impactar, 5 peus d'abast, un objectiu. {@h}14 ({@damage 2d6 + 7}) de dany tallant, o 17 ({@damage 2d6 + 10}) de dany tallant while raging, més 3 ({@damage 1d6}) de dany de foc del guants de fúria flamejant."
					]
				},
				{
					"name": "Banyes",
					"entries": [
						"{@atk mw} {@hit 11} a impactar, 5 peus d'abast, un objectiu. {@h}16 ({@damage 2d8 + 7}) de dany perforant, o 19 ({@damage 2d8 + 10}) de dany perforant mentre ràbia."
					]
				}
			],
			"hasToken": true,
			"senseTags": [
				"D"
			],
			"actionTags": [
				"Multiatac"
			],
			"languageTags": [
				"AB",
				"C"
			],
			"damageTags": [
				"F",
				"P",
				"S"
			],
			"miscTags": [
				"MW"
			],
			"hasFluffImages": true
		},
		{
			"name": "Traxigor",
			"isNpc": true,
			"source": "BGDIA",
			"page": 50,
			"_copy": {
				"name": "Archimat",
				"source": "MM",
				"_mod": {
					"*": {
						"mode": "substituirTxt",
						"replace": "l'arximag",
						"with": "Traxigor",
						"flags": "i"
					},
					"_": {
						"mode": "substituir Encanteris",
						"spells": {
							"7": [
								{
									"replace": "{@spell teleportació}",
									"with": "{@spell saltar de pla}"
								}
							]
						}
					}
				}
			},
			"size": "T",
			"type": "bèstia",
			"alineament": [
				"C",
				"G"
			],
			"str": 3,
			"idiomes": [
				"Comú",
				"Dracònic",
				"Nannès",
				"Gnomesc",
				"Mitjançant",
				"Troglodita"
			],
			"hasToken": true,
			"languageTags": [
				"C",
				"D",
				"DR",
				"G",
				"H",
				"OTH"
			]
		},
		{
			"name": "Tressym",
			"source": "BGDIA",
			"page": 241,
			"otherSources": [
				{
					"source": "IMR"
				}
			],
			"_copy": {
				"name": "Tressym",
				"source": "SKT"
			},
			"type": "monstrositat",
			"hasToken": true,
			"hasFluffImages": true
		},
		{
			"name": "Ulder Ravengard",
			"isNpc": true,
			"source": "BGDIA",
			"page": 70,
			"size": "M",
			"type": {
				"type": "humanoide",
				"tags": [
					"humà"
				]
			},
			"alineament": [
				"N"
			],
			"ac": [
				{
					"ac": 20,
					"from": [
						"{@item armadura de plaques|phb}",
						"{@item shield|phb}"
					]
				}
			],
			"hp": {
				"average": 112,
				"formula": "15d8 + 45"
			},
			"speed": {
				"walk": 25
			},
			"str": 17,
			"dex": 14,
			"con": 16,
			"int": 11,
			"wis": 10,
			"cha": 17,
			"save": {
				"con": "+6",
				"wis": "+3"
			},
			"skill": {
				"athletics": "+6",
				"intimidation": "+6",
				"perception": "+3"
			},
			"passive": 13,
			"idiomes": [
				"Comú"
			],
			"cr": "5",
			"action": [
				{
					"name": "Multiatac",
					"entries": [
						"Ulder fa tres atacs cos a cos, només un dels quals pot ser amb el seu escut."
					]
				},
				{
					"name": "Espasa llarga +1",
					"entries": [
						"{@atk mw} {@hit 7} a impactar, 5 peus d'abast, un objectiu. {@h}8 ({@damage 1d8 + 4}) de dany tallant, o 9 ({@damage 1d10 + 4}) de dany tallant si s'usa amb dos mans."
					]
				},
				{
					"name": "Escut",
					"entries": [
						"{@atk mw} {@hit 6} a impactar, 5 peus d'abast, una criatura. {@h}6 ({@damage 1d6 + 3}) de Dany contundent, i l'Ulder empeny l'objectiu a 5 peus d'ell. Llavors, Ulder entra a l'espai desocupat per l'objectiu. Si l'objectiu és empès a menys de 5 peus d'una criatura amiga d'Ulder, l'objectiu provoca un atac d'oportunitat d'aquesta criatura."
					]
				}
			],
			"reaction": [
				{
					"name": "Vaga de Guardians",
					"entries": [
						"Si un enemic a 5 peus d'Ulder ataca un objectiu que no sigui ell, Ulder pot fer un atac cos a cos contra aquest enemic."
					]
				}
			],
			"hasToken": true,
			"actionTags": [
				"Multiatac"
			],
			"languageTags": [
				"C"
			],
			"damageTags": [
				"B",
				"S"
			],
			"miscTags": [
				"MW"
			],
			"hasFluff": true,
			"hasFluffImages": true
		},
		{
			"name": "Arbre No-mort",
			"source": "BGDIA",
			"page": 109,
			"_copy": {
				"name": "Treant",
				"source": "MM",
				"_mod": {
					"*": {
						"mode": "substituirTxt",
						"replace": "tractant",
						"with": "arbre"
					}
				}
			},
			"type": "no mort",
			"resist": [
				"necròtic"
			],
			"hasToken": true
		}
	]
}